Workbook
Name INSTOCK: INSTOCK!$D$2:$N$6125
Name TABLE: #REF!
Name QTY: #REF!
Name UNITPRICE: #REF!
Name LIST: #REF!
Name TABLEITEM: TABLEITEM!$B$2:$G$2749
Name TABLETEST: #REF!

Sheet INSTOCK
B2: NO. | C2: DATE | D2: IV No. | E2: PO No. | F2: PC Job | G2: SUPPLIER | H2: ID | I2: qty | J2: Column3 | K2: UNIT/Price | L2: group | M2: LIST | N2: Total | O2: Column1 | P2: Column2
B3: 1 | C3: 43199 | D3: ยอดยกมา17 | H3: CG | I3: 102 | J3: =IF(D3<>"",VLOOKUP(H3,TABLEITEM,5,FALSE),"") -> คู่ | K3: 4.58 | L3: =IF(D3<>"",VLOOKUP(H3,TABLEITEM,2,FALSE),"") | M3: =IF(D3<>"",VLOOKUP(H3,TABLEITEM,3,FALSE),"") -> ถุงมือผ้า | N3: =INSTOCK!$I3*INSTOCK!$K3 -> 467.16
B4: 2 | C4: 43199 | D4: ยอดยกมา17 | H4: LG | I4: 13 | J4: =IF(D4<>"",VLOOKUP(H4,TABLEITEM,5,FALSE),"") -> คู่ | K4: 41.66 | L4: =IF(D4<>"",VLOOKUP(H4,TABLEITEM,2,FALSE),"") | M4: =IF(D4<>"",VLOOKUP(H4,TABLEITEM,3,FALSE),"") -> ถุงมือหนัง | N4: =INSTOCK!$I4*INSTOCK!$K4 -> 541.58
B5: 3 | C5: 43199 | D5: ยอดยกมา17 | H5: RP | I5: 195 | J5: =IF(D5<>"",VLOOKUP(H5,TABLEITEM,5,FALSE),"") -> EA | K5: 2.5 | L5: =IF(D5<>"",VLOOKUP(H5,TABLEITEM,2,FALSE),"") | M5: =IF(D5<>"",VLOOKUP(H5,TABLEITEM,3,FALSE),"") -> ผ้าปิดจมูก | N5: =INSTOCK!$I5*INSTOCK!$K5 -> 487.5
B6: 4 | C6: 43199 | D6: ยอดยกมา17 | H6: PVC | I6: 30 | J6: =IF(D6<>"",VLOOKUP(H6,TABLEITEM,5,FALSE),"") -> ROLL | K6: 140 | L6: =IF(D6<>"",VLOOKUP(H6,TABLEITEM,2,FALSE),"") | M6: =IF(D6<>"",VLOOKUP(H6,TABLEITEM,3,FALSE),"") -> พลาสติกห่อตู้ 20micx50cmx300m | N6: =INSTOCK!$I6*INSTOCK!$K6 -> 4200
B7: 5 | C7: 43199 | D7: ยอดยกมา17 | H7: WW | I7: 9 | J7: =IF(D7<>"",VLOOKUP(H7,TABLEITEM,5,FALSE),"") -> ROLL | K7: 750 | L7: =IF(D7<>"",VLOOKUP(H7,TABLEITEM,2,FALSE),"") | M7: =IF(D7<>"",VLOOKUP(H7,TABLEITEM,3,FALSE),"") -> ลวดเชื่อมco2 | N7: =INSTOCK!$I7*INSTOCK!$K7 -> 6750
B8: 6 | C8: 43199 | D8: ยอดยกมา17 | H8: BS | I8: 360 | J8: =IF(D8<>"",VLOOKUP(H8,TABLEITEM,5,FALSE),"") -> EA | K8: 40 | L8: =IF(D8<>"",VLOOKUP(H8,TABLEITEM,2,FALSE),"") | M8: =IF(D8<>"",VLOOKUP(H8,TABLEITEM,3,FALSE),"") -> ใบหินเจียร์ 4'' | N8: =INSTOCK!$I8*INSTOCK!$K8 -> 14400
B9: 7 | C9: 43199 | D9: ยอดยกมา17 | H9: BT80 | I9: 390 | J9: =IF(D9<>"",VLOOKUP(H9,TABLEITEM,5,FALSE),"") -> EA | K9: 42 | L9: =IF(D9<>"",VLOOKUP(H9,TABLEITEM,2,FALSE),"") | M9: =IF(D9<>"",VLOOKUP(H9,TABLEITEM,3,FALSE),"") -> ใบขัดซ้อน # 80 | N9: =INSTOCK!$I9*INSTOCK!$K9 -> 16380
B10: 8 | C10: 43199 | D10: ยอดยกมา17 | H10: BT400 | I10: 110 | J10: =IF(D10<>"",VLOOKUP(H10,TABLEITEM,5,FALSE),"") -> EA | K10: 25 | L10: =IF(D10<>"",VLOOKUP(H10,TABLEITEM,2,FALSE),"") | M10: =IF(D10<>"",VLOOKUP(H10,TABLEITEM,3,FALSE),"") -> ใบขัดซ้อน # 400 | N10: =INSTOCK!$I10*INSTOCK!$K10 -> 2750
B11: 9 | C11: 43199 | D11: ยอดยกมา17 | H11: RS120 | I11: 900 | J11: =IF(D11<>"",VLOOKUP(H11,TABLEITEM,5,FALSE),"") -> EA | K11: 4.5 | L11: =IF(D11<>"",VLOOKUP(H11,TABLEITEM,2,FALSE),"") | M11: =IF(D11<>"",VLOOKUP(H11,TABLEITEM,3,FALSE),"") -> กระดาษทรายกลม#120 | N11: =INSTOCK!$I11*INSTOCK!$K11 -> 4050
B12: 10 | C12: 43199 | D12: ยอดยกมา17 | H12: PW | I12: 10 | J12: =IF(D12<>"",VLOOKUP(H12,TABLEITEM,5,FALSE),"") -> #N/A | K12: 490 | L12: =IF(D12<>"",VLOOKUP(H12,TABLEITEM,2,FALSE),"") -> #N/A | M12: =IF(D12<>"",VLOOKUP(H12,TABLEITEM,3,FALSE),"") -> #N/A | N12: =INSTOCK!$I12*INSTOCK!$K12 -> 4900
B13: 11 | C13: 43199 | D13: ยอดยกมา17 | H13: DC110 | I13: 1200 | J13: =IF(D13<>"",VLOOKUP(H13,TABLEITEM,5,FALSE),"") -> M | K13: 18 | L13: =IF(D13<>"",VLOOKUP(H13,TABLEITEM,2,FALSE),"") | M13: =IF(D13<>"",VLOOKUP(H13,TABLEITEM,3,FALSE),"") -> ยางโปร่ง#110 | N13: =INSTOCK!$I13*INSTOCK!$K13 -> 21600
B14: 12 | C14: 43199 | D14: ยอดยกมา17 | H14: SR 3/4x3/16 | I14: 100 | J14: =IF(D14<>"",VLOOKUP(H14,TABLEITEM,5,FALSE),"") -> M | K14: 12 | L14: =IF(D14<>"",VLOOKUP(H14,TABLEITEM,2,FALSE),"") | M14: =IF(D14<>"",VLOOKUP(H14,TABLEITEM,3,FALSE),"") -> ยางฟองน้ำ 3/4''x3/16'' | N14: =INSTOCK!$I14*INSTOCK!$K14 -> 1200
... B31: 29 | C31: 43199 | D31: ยอดยกมา17 | H31: TN AAA | I31: 3 | J31: =IF(D31<>"",VLOOKUP(H31,TABLEITEM,5,FALSE),"") -> ปี๊ป | K31: 260 | L31: =IF(D31<>"",VLOOKUP(H31,TABLEITEM,2,FALSE),"") | M31: =IF(D31<>"",VLOOKUP(H31,TABLEITEM,3,FALSE),"") -> ทินเนอร์ AAA | N31: =INSTOCK!$I31*INSTOCK!$K31 -> 780
B32: 30 | C32: 43199 | D32: ยอดยกมา17 | H32: PAINT-POUT | I32: 46 | J32: =IF(D32<>"",VLOOKUP(H32,TABLEITEM,5,FALSE),"") -> กล | L32: =IF(D32<>"",VLOOKUP(H32,TABLEITEM,2,FALSE),"") | M32: =IF(D32<>"",VLOOKUP(H32,TABLEITEM,3,FALSE),"") -> สีโป้ว | N32: =INSTOCK!$I32*INSTOCK!$K32 -> 0
B33: 31 | C33: 43199 | D33: ยอดยกมา17 | H33: BW | I33: 12 | J33: =IF(D33<>"",VLOOKUP(H33,TABLEITEM,5,FALSE),"") -> ROLL | K33: 90 | L33: =IF(D33<>"",VLOOKUP(H33,TABLEITEM,2,FALSE),"") | M33: =IF(D33<>"",VLOOKUP(H33,TABLEITEM,3,FALSE),"") -> ลวดดำ | N33: =INSTOCK!$I33*INSTOCK!$K33 -> 1080
B34: 32 | C34: 43199 | D34: ยอดยกมา17 | H34: TSA-W | I34: 18 | J34: =IF(D34<>"",VLOOKUP(H34,TABLEITEM,5,FALSE),"") -> EA | L34: =IF(D34<>"",VLOOKUP(H34,TABLEITEM,2,FALSE),"") | M34: =IF(D34<>"",VLOOKUP(H34,TABLEITEM,3,FALSE),"") -> กระดาษกาว 2หน้าสีขาว | N34: =INSTOCK!$I34*INSTOCK!$K34 -> 0
B35: 33 | C35: 43199 | D35: ยอดยกมา17 | H35: TSA-4 | I35: 13 | J35: =IF(D35<>"",VLOOKUP(H35,TABLEITEM,5,FALSE),"") -> EA | K35: 5.5 | L35: =IF(D35<>"",VLOOKUP(H35,TABLEITEM,2,FALSE),"") | M35: =IF(D35<>"",VLOOKUP(H35,TABLEITEM,3,FALSE),"") -> กระดาษกาว 2หน้า 4มิล | N35: =INSTOCK!$I35*INSTOCK!$K35 -> 71.5
B36: 34 | C36: 43199 | D36: ยอดยกมา17 | H36: TSA-8 | I36: 30 | J36: =IF(D36<>"",VLOOKUP(H36,TABLEITEM,5,FALSE),"") -> EA | K36: 123 | L36: =IF(D36<>"",VLOOKUP(H36,TABLEITEM,2,FALSE),"") | M36: =IF(D36<>"",VLOOKUP(H36,TABLEITEM,3,FALSE),"") -> กระดาษกาว2 หน้า 8 มิล | N36: =INSTOCK!$I36*INSTOCK!$K36 -> 3690
B37: 35 | C37: 43199 | D37: ยอดยกมา17 | H37: TSA-13 | I37: 98 | J37: =IF(D37<>"",VLOOKUP(H37,TABLEITEM,5,FALSE),"") -> EA | K37: 159 | L37: =IF(D37<>"",VLOOKUP(H37,TABLEITEM,2,FALSE),"") | M37: =IF(D37<>"",VLOOKUP(H37,TABLEITEM,3,FALSE),"") -> กระดาษกาว 2 หน้า 13 มิล | N37: =INSTOCK!$I37*INSTOCK!$K37 -> 15582
B38: 36 | C38: 43199 | D38: ยอดยกมา17 | H38: NITT0 | I38: 35 | J38: =IF(D38<>"",VLOOKUP(H38,TABLEITEM,5,FALSE),"") -> EA | K38: 18 | L38: =IF(D38<>"",VLOOKUP(H38,TABLEITEM,2,FALSE),"") | M38: =IF(D38<>"",VLOOKUP(H38,TABLEITEM,3,FALSE),"") -> กระดาษกาวนิตโต้ | N38: =INSTOCK!$I38*INSTOCK!$K38 -> 630
B39: 37 | C39: 43199 | D39: ยอดยกมา17 | H39: GT1 | I39: 16 | J39: =IF(D39<>"",VLOOKUP(H39,TABLEITEM,5,FALSE),"") -> EA | K39: 26 | L39: =IF(D39<>"",VLOOKUP(H39,TABLEITEM,2,FALSE),"") | M39: =IF(D39<>"",VLOOKUP(H39,TABLEITEM,3,FALSE),"") -> กระดาษกาว 1 '' | N39: =INSTOCK!$I39*INSTOCK!$K39 -> 416
B40: 38 | C40: 43199 | D40: ยอดยกมา17 | H40: GT2 | I40: 12 | J40: =IF(D40<>"",VLOOKUP(H40,TABLEITEM,5,FALSE),"") -> EA | K40: 47 | L40: =IF(D40<>"",VLOOKUP(H40,TABLEITEM,2,FALSE),"") | M40: =IF(D40<>"",VLOOKUP(H40,TABLEITEM,3,FALSE),"") -> กระดาษกาว 2 '' | N40: =INSTOCK!$I40*INSTOCK!$K40 -> 564
B41: 39 | C41: 43199 | D41: ยอดยกมา17 | H41: GT3 | I41: 80 | J41: =IF(D41<>"",VLOOKUP(H41,TABLEITEM,5,FALSE),"") -> EA | L41: =IF(D41<>"",VLOOKUP(H41,TABLEITEM,2,FALSE),"") | M41: =IF(D41<>"",VLOOKUP(H41,TABLEITEM,3,FALSE),"") -> กระดาษกาว 3 '' | N41: =INSTOCK!$I41*INSTOCK!$K41 -> 0
B42: 40 | C42: 43199 | D42: ยอดยกมา17 | H42: CAT | I42: 39 | J42: =IF(D42<>"",VLOOKUP(H42,TABLEITEM,5,FALSE),"") -> EA | K42: 35.04 | L42: =IF(D42<>"",VLOOKUP(H42,TABLEITEM,2,FALSE),"") | M42: =IF(D42<>"",VLOOKUP(H42,TABLEITEM,3,FALSE),"") -> เทปใส 2'' | N42: =INSTOCK!$I42*INSTOCK!$K42 -> 1366.56
B43: 41 | C43: 43199 | D43: ยอดยกมา17 | H43: BCT | I43: 63 | J43: =IF(D43<>"",VLOOKUP(H43,TABLEITEM,5,FALSE),"") -> EA | K43: 10 | L43: =IF(D43<>"",VLOOKUP(H43,TABLEITEM,2,FALSE),"") | M43: =IF(D43<>"",VLOOKUP(H43,TABLEITEM,3,FALSE),"") -> เทปพันสายไฟสีดำ | N43: =INSTOCK!$I43*INSTOCK!$K43 -> 630
B44: 42 | C44: 43199 | D44: ยอดยกมา17 | H44: PT | I44: 27 | J44: =IF(D44<>"",VLOOKUP(H44,TABLEITEM,5,FALSE),"") -> EA | K44: 10 | L44: =IF(D44<>"",VLOOKUP(H44,TABLEITEM,2,FALSE),"") | M44: =IF(D44<>"",VLOOKUP(H44,TABLEITEM,3,FALSE),"") -> เทปพันเกลียว | N44: =INSTOCK!$I44*INSTOCK!$K44 -> 270
B45: 43 | C45: 43199 | D45: ยอดยกมา17 | H45: paint-231 | I45: 12 | J45: =IF(D45<>"",VLOOKUP(H45,TABLEITEM,5,FALSE),"") -> กป. | K45: 41.6 | L45: =IF(D45<>"",VLOOKUP(H45,TABLEITEM,2,FALSE),"") | M45: =IF(D45<>"",VLOOKUP(H45,TABLEITEM,3,FALSE),"") -> สีสเปรย์ เคลียร์ | N45: =INSTOCK!$I45*INSTOCK!$K45 -> 499.2
B46: 44 | C46: 43199 | D46: ยอดยกมา17 | H46: SONAX | I46: 5 | J46: =IF(D46<>"",VLOOKUP(H46,TABLEITEM,5,FALSE),"") -> EA | K46: 100 | L46: =IF(D46<>"",VLOOKUP(H46,TABLEITEM,2,FALSE),"") | M46: =IF(D46<>"",VLOOKUP(H46,TABLEITEM,3,FALSE),"") -> โซเน็ก | N46: =INSTOCK!$I46*INSTOCK!$K46 -> 500
B47: 45 | C47: 43199 | D47: ยอดยกมา17 | H47: GLUE | I47: 1 | J47: =IF(D47<>"",VLOOKUP(H47,TABLEITEM,5,FALSE),"") -> EA | K47: 65 | L47: =IF(D47<>"",VLOOKUP(H47,TABLEITEM,2,FALSE),"") | M47: =IF(D47<>"",VLOOKUP(H47,TABLEITEM,3,FALSE),"") -> กาวยาง | N47: =INSTOCK!$I47*INSTOCK!$K47 -> 65
B48: 46 | C48: 43199 | D48: ยอดยกมา17 | H48: paint-211 | I48: 35 | J48: =IF(D48<>"",VLOOKUP(H48,TABLEITEM,5,FALSE),"") -> กป. | K48: 41.6 | L48: =IF(D48<>"",VLOOKUP(H48,TABLEITEM,2,FALSE),"") | M48: =IF(D48<>"",VLOOKUP(H48,TABLEITEM,3,FALSE),"") -> สีสเปรย์ สีแดง | N48: =INSTOCK!$I48*INSTOCK!$K48 -> 1456
B49: 47 | C49: 43199 | D49: ยอดยกมา17 | H49: paint-216 | I49: 32 | J49: =IF(D49<>"",VLOOKUP(H49,TABLEITEM,5,FALSE),"") -> กป. | K49: 41.6 | L49: =IF(D49<>"",VLOOKUP(H49,TABLEITEM,2,FALSE),"") | M49: =IF(D49<>"",VLOOKUP(H49,TABLEITEM,3,FALSE),"") -> สีสเปรย์ สีน้ำเงิน | N49: =INSTOCK!$I49*INSTOCK!$K49 -> 1331.2
B50: 48 | C50: 43199 | D50: ยอดยกมา17 | H50: paint-200 | I50: 28 | J50: =IF(D50<>"",VLOOKUP(H50,TABLEITEM,5,FALSE),"") -> กป. | K50: 41.6 | L50: =IF(D50<>"",VLOOKUP(H50,TABLEITEM,2,FALSE),"") | M50: =IF(D50<>"",VLOOKUP(H50,TABLEITEM,3,FALSE),"") -> สีสเปรย์ สีขาว | N50: =INSTOCK!$I50*INSTOCK!$K50 -> 1164.8
B51: 49 | C51: 43199 | D51: ยอดยกมา17 | H51: paint-218 | I51: 24 | J51: =IF(D51<>"",VLOOKUP(H51,TABLEITEM,5,FALSE),"") -> กป. | K51: 41.6 | L51: =IF(D51<>"",VLOOKUP(H51,TABLEITEM,2,FALSE),"") | M51: =IF(D51<>"",VLOOKUP(H51,TABLEITEM,3,FALSE),"") -> สีสเปรย์ สีเหลือง | N51: =INSTOCK!$I51*INSTOCK!$K51 -> 998.4
B52: 50 | C52: 43199 | D52: ยอดยกมา17 | H52: paint-214 | I52: 7 | J52: =IF(D52<>"",VLOOKUP(H52,TABLEITEM,5,FALSE),"") -> กป. | K52: 41.6 | L52: =IF(D52<>"",VLOOKUP(H52,TABLEITEM,2,FALSE),"") | M52: =IF(D52<>"",VLOOKUP(H52,TABLEITEM,3,FALSE),"") -> สีสเปรย์ สีเขียว | N52: =INSTOCK!$I52*INSTOCK!$K52 -> 291.2
B53: 51 | C53: 43199 | D53: ยอดยกมา17 | H53: paint-210 | I53: 20 | J53: =IF(D53<>"",VLOOKUP(H53,TABLEITEM,5,FALSE),"") -> กป. | K53: 41.6 | L53: =IF(D53<>"",VLOOKUP(H53,TABLEITEM,2,FALSE),"") | M53: =IF(D53<>"",VLOOKUP(H53,TABLEITEM,3,FALSE),"") -> สีสเปรย์ สีดำ | N53: =INSTOCK!$I53*INSTOCK!$K53 -> 832
... B114: 112 | C114: 43199 | D114: ยอดยกมา17 | H114: keyFD-14 | I114: 338 | J114: =IF(D114<>"",VLOOKUP(H114,TABLEITEM,5,FALSE),"") -> EA | K114: 19 | L114: =IF(D114<>"",VLOOKUP(H114,TABLEITEM,2,FALSE),"") | M114: =IF(D114<>"",VLOOKUP(H114,TABLEITEM,3,FALSE),"") -> กุญแจหูกระเป๋าสแตนเลสตัวเล็กFD-14 | N114: =INSTOCK!$I114*INSTOCK!$K114 -> 6422
B115: 113 | C115: 43199 | D115: ยอดยกมา17 | H115: keyFD-13 | I115: 204 | J115: =IF(D115<>"",VLOOKUP(H115,TABLEITEM,5,FALSE),"") -> EA | L115: =IF(D115<>"",VLOOKUP(H115,TABLEITEM,2,FALSE),"") | M115: =IF(D115<>"",VLOOKUP(H115,TABLEITEM,3,FALSE),"") -> กุญแจหูกระเป๋าสแตนเลสตัวใหญ่FD-13 | N115: =INSTOCK!$I115*INSTOCK!$K115 -> 0
B116: 114 | C116: 43199 | D116: ยอดยกมา17 | H116: keyAB-301 | I116: 130 | J116: =IF(D116<>"",VLOOKUP(H116,TABLEITEM,5,FALSE),"") -> EA | K116: 90 | L116: =IF(D116<>"",VLOOKUP(H116,TABLEITEM,2,FALSE),"") | M116: =IF(D116<>"",VLOOKUP(H116,TABLEITEM,3,FALSE),"") -> DOOR LOCKER AB301-3-1 | N116: =INSTOCK!$I116*INSTOCK!$K116 -> 11700
B117: 115 | C117: 43199 | D117: ยอดยกมา17 | H117: key261-91H | I117: 10 | J117: =IF(D117<>"",VLOOKUP(H117,TABLEITEM,5,FALSE),"") -> EA | K117: 63.75 | L117: =IF(D117<>"",VLOOKUP(H117,TABLEITEM,2,FALSE),"") | M117: =IF(D117<>"",VLOOKUP(H117,TABLEITEM,3,FALSE),"") -> มือจับ 1A-261-91-H | N117: =INSTOCK!$I117*INSTOCK!$K117 -> 637.5
B118: 116 | C118: 43199 | D118: ยอดยกมา17 | H118: C4 | I118: 421 | J118: =IF(D118<>"",VLOOKUP(H118,TABLEITEM,5,FALSE),"") -> EA | K118: 45 | L118: =IF(D118<>"",VLOOKUP(H118,TABLEITEM,2,FALSE),"") | M118: =IF(D118<>"",VLOOKUP(H118,TABLEITEM,3,FALSE),"") -> มือจับตัวซี 4 นิ้ว มือจับโครเมี่ยม | N118: =INSTOCK!$I118*INSTOCK!$K118 -> 18945
B119: 117 | C119: 43199 | D119: ยอดยกมา17 | H119: PL006 | I119: 114 | J119: =IF(D119<>"",VLOOKUP(H119,TABLEITEM,5,FALSE),"") -> EA | K119: 20 | L119: =IF(D119<>"",VLOOKUP(H119,TABLEITEM,2,FALSE),"") | M119: =IF(D119<>"",VLOOKUP(H119,TABLEITEM,3,FALSE),"") -> มือจับพลาสติกสีดำ | N119: =INSTOCK!$I119*INSTOCK!$K119 -> 2280
B120: 118 | C120: 43199 | D120: ยอดยกมา17 | H120: 1K077-01 | I120: 55 | J120: =IF(D120<>"",VLOOKUP(H120,TABLEITEM,5,FALSE),"") -> EA | K120: 10 | L120: =IF(D120<>"",VLOOKUP(H120,TABLEITEM,2,FALSE),"") | M120: =IF(D120<>"",VLOOKUP(H120,TABLEITEM,3,FALSE),"") -> ลูกไข | N120: =INSTOCK!$I120*INSTOCK!$K120 -> 550
B121: 119 | C121: 43199 | D121: ยอดยกมา17 | H121: KEYLOCK | I121: 1150 | J121: =IF(D121<>"",VLOOKUP(H121,TABLEITEM,5,FALSE),"") -> EA | L121: =IF(D121<>"",VLOOKUP(H121,TABLEITEM,2,FALSE),"") | M121: =IF(D121<>"",VLOOKUP(H121,TABLEITEM,3,FALSE),"") -> ตัวล็อคกุญแจ | N121: =INSTOCK!$I121*INSTOCK!$K121 -> 0
B122: 120 | C122: 43199 | D122: ยอดยกมา17 | H122: SSBN-09 | I122: 59 | J122: =IF(D122<>"",VLOOKUP(H122,TABLEITEM,5,FALSE),"") -> EA | L122: =IF(D122<>"",VLOOKUP(H122,TABLEITEM,2,FALSE),"") | M122: =IF(D122<>"",VLOOKUP(H122,TABLEITEM,3,FALSE),"") -> ปุ่มมือจับสแตนเลส | N122: =INSTOCK!$I122*INSTOCK!$K122 -> 0
B123: 121 | C123: 43199 | D123: ยอดยกมา17 | H123: TL | I123: 197 | J123: =IF(D123<>"",VLOOKUP(H123,TABLEITEM,5,FALSE),"") -> EA | K123: 23 | L123: =IF(D123<>"",VLOOKUP(H123,TABLEITEM,2,FALSE),"") | M123: =IF(D123<>"",VLOOKUP(H123,TABLEITEM,3,FALSE),"") -> มือจับตู้โหลด | N123: =INSTOCK!$I123*INSTOCK!$K123 -> 4531
B124: 122 | C124: 43199 | D124: ยอดยกมา17 | H124: CVGR | I124: 2983 | J124: =IF(D124<>"",VLOOKUP(H124,TABLEITEM,5,FALSE),"") -> EA | K124: 3.5 | L124: =IF(D124<>"",VLOOKUP(H124,TABLEITEM,2,FALSE),"") | M124: =IF(D124<>"",VLOOKUP(H124,TABLEITEM,3,FALSE),"") -> COVER KEY สีเทา | N124: =INSTOCK!$I124*INSTOCK!$K124 -> 10440.5
B125: 123 | C125: 43199 | D125: ยอดยกมา17 | H125: CVCR | I125: 1869 | J125: =IF(D125<>"",VLOOKUP(H125,TABLEITEM,5,FALSE),"") -> EA | K125: 3.5 | L125: =IF(D125<>"",VLOOKUP(H125,TABLEITEM,2,FALSE),"") | M125: =IF(D125<>"",VLOOKUP(H125,TABLEITEM,3,FALSE),"") -> COVER KEY สีครีม | N125: =INSTOCK!$I125*INSTOCK!$K125 -> 6541.5
B126: 124 | C126: 43199 | D126: ยอดยกมา17 | H126: keyA-464-1-1 | I126: 582 | J126: =IF(D126<>"",VLOOKUP(H126,TABLEITEM,5,FALSE),"") -> EA | K126: 535 | L126: =IF(D126<>"",VLOOKUP(H126,TABLEITEM,2,FALSE),"") | M126: =IF(D126<>"",VLOOKUP(H126,TABLEITEM,3,FALSE),"") -> กุญแจ TAKIGEN A 464-1-1 | N126: =INSTOCK!$I126*INSTOCK!$K126 -> 311370
B127: 125 | C127: 43199 | D127: ยอดยกมา17 | H127: keyA-51-1-1 | I127: 0 | J127: =IF(D127<>"",VLOOKUP(H127,TABLEITEM,5,FALSE),"") -> EA | K127: 630 | L127: =IF(D127<>"",VLOOKUP(H127,TABLEITEM,2,FALSE),"") | M127: =IF(D127<>"",VLOOKUP(H127,TABLEITEM,3,FALSE),"") -> กุญแจ TAKIGEN A-51-1-1 | N127: =INSTOCK!$I127*INSTOCK!$K127 -> 0
B128: 126 | C128: 43199 | D128: ยอดยกมา17 | H128: keyA-140-1-1 | I128: 771 | J128: =IF(D128<>"",VLOOKUP(H128,TABLEITEM,5,FALSE),"") -> EA | K128: 420 | L128: =IF(D128<>"",VLOOKUP(H128,TABLEITEM,2,FALSE),"") | M128: =IF(D128<>"",VLOOKUP(H128,TABLEITEM,3,FALSE),"") -> กุญแจ TAKIGEN A-140-1-1 | N128: =INSTOCK!$I128*INSTOCK!$K128 -> 323820
B129: 127 | C129: 43199 | D129: ยอดยกมา17 | H129: keyA-1140 | I129: 1 | J129: =IF(D129<>"",VLOOKUP(H129,TABLEITEM,5,FALSE),"") -> EA | K129: 2300 | L129: =IF(D129<>"",VLOOKUP(H129,TABLEITEM,2,FALSE),"") | M129: =IF(D129<>"",VLOOKUP(H129,TABLEITEM,3,FALSE),"") -> กุญแจเขาควายกันน้ำ A-1140-2-1-sus | N129: =INSTOCK!$I129*INSTOCK!$K129 -> 2300
B130: 128 | C130: 43199 | D130: ยอดยกมา17 | H130: keyC-1012 | I130: 988 | J130: =IF(D130<>"",VLOOKUP(H130,TABLEITEM,5,FALSE),"") -> EA | K130: 59 | L130: =IF(D130<>"",VLOOKUP(H130,TABLEITEM,2,FALSE),"") | M130: =IF(D130<>"",VLOOKUP(H130,TABLEITEM,3,FALSE),"") -> กุญแจหูกระเป๋าเล็ก SUS C-1012-2-1 | N130: =INSTOCK!$I130*INSTOCK!$K130 -> 58292
B131: 129 | C131: 43199 | D131: ยอดยกมา17 | H131: keyC-1007 | I131: 50 | J131: =IF(D131<>"",VLOOKUP(H131,TABLEITEM,5,FALSE),"") -> EA | K131: 10 | L131: =IF(D131<>"",VLOOKUP(H131,TABLEITEM,2,FALSE),"") | M131: =IF(D131<>"",VLOOKUP(H131,TABLEITEM,3,FALSE),"") -> กุญแจหูกระเป๋าสปริงC-1007-2 | N131: =INSTOCK!$I131*INSTOCK!$K131 -> 500
B132: 130 | C132: 43199 | D132: ยอดยกมา17 | H132: Hing02 | I132: 27 | J132: =IF(D132<>"",VLOOKUP(H132,TABLEITEM,5,FALSE),"") -> EA | K132: 22 | L132: =IF(D132<>"",VLOOKUP(H132,TABLEITEM,2,FALSE),"") | M132: =IF(D132<>"",VLOOKUP(H132,TABLEITEM,3,FALSE),"") -> HING สีเงิน1-170-03 | N132: =INSTOCK!$I132*INSTOCK!$K132 -> 594
B133: 131 | C133: 43199 | D133: ยอดยกมา17 | H133: Hing01 | I133: 160 | J133: =IF(D133<>"",VLOOKUP(H133,TABLEITEM,5,FALSE),"") -> EA | K133: 22 | L133: =IF(D133<>"",VLOOKUP(H133,TABLEITEM,2,FALSE),"") | M133: =IF(D133<>"",VLOOKUP(H133,TABLEITEM,3,FALSE),"") -> HING สีดำตัวใหญ่1-174-04 | N133: =INSTOCK!$I133*INSTOCK!$K133 -> 3520
B134: 132 | C134: 43199 | D134: ยอดยกมา17 | H134: keyHL-027 | I134: 99 | J134: =IF(D134<>"",VLOOKUP(H134,TABLEITEM,5,FALSE),"") -> EA | K134: 35 | L134: =IF(D134<>"",VLOOKUP(H134,TABLEITEM,2,FALSE),"") | M134: =IF(D134<>"",VLOOKUP(H134,TABLEITEM,3,FALSE),"") -> KEY-LOCKHINGES HL-027 | N134: =INSTOCK!$I134*INSTOCK!$K134 -> 3465
... B137: 135 | C137: 43199 | D137: ยอดยกมา17 | H137: SSH-112 | I137: 197 | J137: =IF(D137<>"",VLOOKUP(H137,TABLEITEM,5,FALSE),"") -> EA | K137: 8.8 | L137: =IF(D137<>"",VLOOKUP(H137,TABLEITEM,2,FALSE),"") | M137: =IF(D137<>"",VLOOKUP(H137,TABLEITEM,3,FALSE),"") -> บานพับ 1''1/2 สแตนเลส | N137: =INSTOCK!$I137*INSTOCK!$K137 -> 1733.6
B138: 136 | C138: 43199 | D138: ยอดยกมา17 | H138: PA-100B | I138: 336 | J138: =IF(D138<>"",VLOOKUP(H138,TABLEITEM,5,FALSE),"") -> EA | L138: =IF(D138<>"",VLOOKUP(H138,TABLEITEM,2,FALSE),"") | M138: =IF(D138<>"",VLOOKUP(H138,TABLEITEM,3,FALSE),"") -> ยางกันกระแทกจิ๋ว | N138: =INSTOCK!$I138*INSTOCK!$K138 -> 0
B139: 137 | C139: 43199 | D139: ยอดยกมา17 | H139: PA-150B | I139: 1793 | J139: =IF(D139<>"",VLOOKUP(H139,TABLEITEM,5,FALSE),"") -> EA | K139: 2.5 | L139: =IF(D139<>"",VLOOKUP(H139,TABLEITEM,2,FALSE),"") | M139: =IF(D139<>"",VLOOKUP(H139,TABLEITEM,3,FALSE),"") -> ยางกันกระแทกเล็ก | N139: =INSTOCK!$I139*INSTOCK!$K139 -> 4482.5
B140: 138 | C140: 43199 | D140: ยอดยกมา17 | H140: PA-200B | I140: 141 | J140: =IF(D140<>"",VLOOKUP(H140,TABLEITEM,5,FALSE),"") -> EA | L140: =IF(D140<>"",VLOOKUP(H140,TABLEITEM,2,FALSE),"") | M140: =IF(D140<>"",VLOOKUP(H140,TABLEITEM,3,FALSE),"") -> ยางกันกระแทกกลาง | N140: =INSTOCK!$I140*INSTOCK!$K140 -> 0
B141: 139 | C141: 43199 | D141: ยอดยกมา17 | H141: PA-250B | I141: 422 | J141: =IF(D141<>"",VLOOKUP(H141,TABLEITEM,5,FALSE),"") -> EA | L141: =IF(D141<>"",VLOOKUP(H141,TABLEITEM,2,FALSE),"") | M141: =IF(D141<>"",VLOOKUP(H141,TABLEITEM,3,FALSE),"") -> ยางกันกระแทกใหญ่ | N141: =INSTOCK!$I141*INSTOCK!$K141 -> 0
B142: 140 | C142: 43199 | D142: ยอดยกมา17 | H142: PA-00B | I142: 53 | J142: =IF(D142<>"",VLOOKUP(H142,TABLEITEM,5,FALSE),"") -> EA | L142: =IF(D142<>"",VLOOKUP(H142,TABLEITEM,2,FALSE),"") | M142: =IF(D142<>"",VLOOKUP(H142,TABLEITEM,3,FALSE),"") -> ยางกันกระแทกมีก้าน | N142: =INSTOCK!$I142*INSTOCK!$K142 -> 0
B143: 141 | C143: 43199 | D143: ยอดยกมา17 | H143: SM-20-BR | I143: 34 | J143: =IF(D143<>"",VLOOKUP(H143,TABLEITEM,5,FALSE),"") -> EA | K143: 9.6 | L143: =IF(D143<>"",VLOOKUP(H143,TABLEITEM,2,FALSE),"") | M143: =IF(D143<>"",VLOOKUP(H143,TABLEITEM,3,FALSE),"") -> แม่เหล็กสีน้าตาล | N143: =INSTOCK!$I143*INSTOCK!$K143 -> 326.4
B144: 142 | C144: 43199 | D144: ยอดยกมา17 | H144: KEY A-140-2-1 | I144: 20 | J144: =IF(D144<>"",VLOOKUP(H144,TABLEITEM,5,FALSE),"") -> EA | K144: 622 | L144: =IF(D144<>"",VLOOKUP(H144,TABLEITEM,2,FALSE),"") | M144: =IF(D144<>"",VLOOKUP(H144,TABLEITEM,3,FALSE),"") -> กุญแจ TAKIGEN A-140-2-1 | N144: =INSTOCK!$I144*INSTOCK!$K144 -> 12440
B145: 143 | C145: 43199 | D145: ยอดยกมา17 | H145: KEY A-140-3-1 | I145: 0 | J145: =IF(D145<>"",VLOOKUP(H145,TABLEITEM,5,FALSE),"") -> EA | K145: 622 | L145: =IF(D145<>"",VLOOKUP(H145,TABLEITEM,2,FALSE),"") | M145: =IF(D145<>"",VLOOKUP(H145,TABLEITEM,3,FALSE),"") -> กุญแจ TAKIGEN A-140-3-1 | N145: =INSTOCK!$I145*INSTOCK!$K145 -> 0
B146: 144 | C146: 43199 | D146: ยอดยกมา17 | H146: CBT4-WH | I146: 5200 | J146: =IF(D146<>"",VLOOKUP(H146,TABLEITEM,5,FALSE),"") -> EA | K146: 0.16 | L146: =IF(D146<>"",VLOOKUP(H146,TABLEITEM,2,FALSE),"") | M146: =IF(D146<>"",VLOOKUP(H146,TABLEITEM,3,FALSE),"") -> เคเบิ้ลไทร์ 4" สีขาวCT-100-2C | N146: =INSTOCK!$I146*INSTOCK!$K146 -> 832
B147: 145 | C147: 43199 | D147: ยอดยกมา17 | H147: CBT4-BK | I147: 1100 | J147: =IF(D147<>"",VLOOKUP(H147,TABLEITEM,5,FALSE),"") -> EA | K147: 0.18 | L147: =IF(D147<>"",VLOOKUP(H147,TABLEITEM,2,FALSE),"") | M147: =IF(D147<>"",VLOOKUP(H147,TABLEITEM,3,FALSE),"") -> เคเบิ้ลไทร์ 4" สีดำCT-100-B-2C | N147: =INSTOCK!$I147*INSTOCK!$K147 -> 198
B148: 146 | C148: 43199 | D148: ยอดยกมา17 | H148: CBT6-WH | I148: 1300 | J148: =IF(D148<>"",VLOOKUP(H148,TABLEITEM,5,FALSE),"") -> EA | K148: 0.45 | L148: =IF(D148<>"",VLOOKUP(H148,TABLEITEM,2,FALSE),"") | M148: =IF(D148<>"",VLOOKUP(H148,TABLEITEM,3,FALSE),"") -> เคเบิ้ลไทร์ 6" สีขาวCT-150-3C | N148: =INSTOCK!$I148*INSTOCK!$K148 -> 585
B149: 147 | C149: 43199 | D149: ยอดยกมา17 | H149: CBT6-BK | I149: 2300 | J149: =IF(D149<>"",VLOOKUP(H149,TABLEITEM,5,FALSE),"") -> EA | K149: 0.45 | L149: =IF(D149<>"",VLOOKUP(H149,TABLEITEM,2,FALSE),"") | M149: =IF(D149<>"",VLOOKUP(H149,TABLEITEM,3,FALSE),"") -> เคเบิ้ลไทร์ 6" สีดำCT-150B-3C | N149: =INSTOCK!$I149*INSTOCK!$K149 -> 1035
B150: 148 | C150: 43199 | D150: ยอดยกมา17 | H150: CBT8-WH | I150: 1700 | J150: =IF(D150<>"",VLOOKUP(H150,TABLEITEM,5,FALSE),"") -> EA | K150: 0.69 | L150: =IF(D150<>"",VLOOKUP(H150,TABLEITEM,2,FALSE),"") | M150: =IF(D150<>"",VLOOKUP(H150,TABLEITEM,3,FALSE),"") -> เคเบิ้ลไทร์ 8" สีขาวCT-200-3C | N150: =INSTOCK!$I150*INSTOCK!$K150 -> 1173
B151: 149 | C151: 43199 | D151: ยอดยกมา17 | H151: CBT8-BK | I151: 3600 | J151: =IF(D151<>"",VLOOKUP(H151,TABLEITEM,5,FALSE),"") -> EA | K151: 0.79 | L151: =IF(D151<>"",VLOOKUP(H151,TABLEITEM,2,FALSE),"") | M151: =IF(D151<>"",VLOOKUP(H151,TABLEITEM,3,FALSE),"") -> เคเบิ้ลไทร์ 8" สีดำCT-200B-3C | N151: =INSTOCK!$I151*INSTOCK!$K151 -> 2844
B152: 150 | C152: 43199 | D152: ยอดยกมา17 | H152: CBT12-WH | I152: 2200 | J152: =IF(D152<>"",VLOOKUP(H152,TABLEITEM,5,FALSE),"") -> EA | K152: 1.48 | L152: =IF(D152<>"",VLOOKUP(H152,TABLEITEM,2,FALSE),"") | M152: =IF(D152<>"",VLOOKUP(H152,TABLEITEM,3,FALSE),"") -> เคเบิ้ลไทร์ 12" สีขาวCT-310-4C | N152: =INSTOCK!$I152*INSTOCK!$K152 -> 3256
B153: 151 | C153: 43199 | D153: ยอดยกมา17 | H153: CBT12-BK | I153: 700 | J153: =IF(D153<>"",VLOOKUP(H153,TABLEITEM,5,FALSE),"") -> EA | K153: 1.7 | L153: =IF(D153<>"",VLOOKUP(H153,TABLEITEM,2,FALSE),"") | M153: =IF(D153<>"",VLOOKUP(H153,TABLEITEM,3,FALSE),"") -> เคเบิ้ลไทร์ 12" สีดำCT-310B-4C | N153: =INSTOCK!$I153*INSTOCK!$K153 -> 1190
B154: 152 | C154: 43199 | D154: ยอดยกมา17 | H154: TV-6 | I154: 309 | J154: =IF(D154<>"",VLOOKUP(H154,TABLEITEM,5,FALSE),"") -> M | K154: 6 | L154: =IF(D154<>"",VLOOKUP(H154,TABLEITEM,2,FALSE),"") | M154: =IF(D154<>"",VLOOKUP(H154,TABLEITEM,3,FALSE),"") -> ไส้ไก่ NO.6 | N154: =INSTOCK!$I154*INSTOCK!$K154 -> 1854
... B168: 166 | C168: 43199 | D168: ยอดยกมา17 | H168: PG20 | I168: 30 | J168: =IF(D168<>"",VLOOKUP(H168,TABLEITEM,5,FALSE),"") -> EA | K168: 24 | L168: =IF(D168<>"",VLOOKUP(H168,TABLEITEM,2,FALSE),"") | M168: =IF(D168<>"",VLOOKUP(H168,TABLEITEM,3,FALSE),"") -> เคเบิ้ลแกรนด์ PG21 | N168: =INSTOCK!$I168*INSTOCK!$K168 -> 720
B169: 167 | C169: 43199 | D169: ยอดยกมา17 | H169: HP-10 | I169: 0 | J169: =IF(D169<>"",VLOOKUP(H169,TABLEITEM,5,FALSE),"") -> EA | L169: =IF(D169<>"",VLOOKUP(H169,TABLEITEM,2,FALSE),"") | M169: =IF(D169<>"",VLOOKUP(H169,TABLEITEM,3,FALSE),"") -> โฮปลั๊ก 10 มิล | N169: =INSTOCK!$I169*INSTOCK!$K169 -> 0
B170: 168 | C170: 43199 | D170: ยอดยกมา17 | H170: HP-22 | I170: 76 | J170: =IF(D170<>"",VLOOKUP(H170,TABLEITEM,5,FALSE),"") -> EA | L170: =IF(D170<>"",VLOOKUP(H170,TABLEITEM,2,FALSE),"") | M170: =IF(D170<>"",VLOOKUP(H170,TABLEITEM,3,FALSE),"") -> โฮปลั๊ก 22 มิล | N170: =INSTOCK!$I170*INSTOCK!$K170 -> 0
B171: 169 | C171: 43199 | D171: ยอดยกมา17 | H171: HP-25 | I171: 70 | J171: =IF(D171<>"",VLOOKUP(H171,TABLEITEM,5,FALSE),"") -> EA | L171: =IF(D171<>"",VLOOKUP(H171,TABLEITEM,2,FALSE),"") | M171: =IF(D171<>"",VLOOKUP(H171,TABLEITEM,3,FALSE),"") -> โฮปลั๊ก 25 มิล | N171: =INSTOCK!$I171*INSTOCK!$K171 -> 0
B172: 170 | C172: 43199 | D172: ยอดยกมา17 | H172: HP-30 | I172: 52 | J172: =IF(D172<>"",VLOOKUP(H172,TABLEITEM,5,FALSE),"") -> EA | L172: =IF(D172<>"",VLOOKUP(H172,TABLEITEM,2,FALSE),"") | M172: =IF(D172<>"",VLOOKUP(H172,TABLEITEM,3,FALSE),"") -> โฮปลั๊ก 30 มิล | N172: =INSTOCK!$I172*INSTOCK!$K172 -> 0
B173: 171 | C173: 43199 | D173: ยอดยกมา17 | H173: NP | I173: 909 | J173: =IF(D173<>"",VLOOKUP(H173,TABLEITEM,5,FALSE),"") -> EA | K173: 8 | L173: =IF(D173<>"",VLOOKUP(H173,TABLEITEM,2,FALSE),"") | M173: =IF(D173<>"",VLOOKUP(H173,TABLEITEM,3,FALSE),"") -> ซองเนมเพลท 20x65 | N173: =INSTOCK!$I173*INSTOCK!$K173 -> 7272
B174: 172 | C174: 43199 | D174: ยอดยกมา17 | H174: PP | I174: 3087 | J174: =IF(D174<>"",VLOOKUP(H174,TABLEITEM,5,FALSE),"") -> EA | K174: 1 | L174: =IF(D174<>"",VLOOKUP(H174,TABLEITEM,2,FALSE),"") | M174: =IF(D174<>"",VLOOKUP(H174,TABLEITEM,3,FALSE),"") -> หมุดเนมเพลท | N174: =INSTOCK!$I174*INSTOCK!$K174 -> 3087
B175: 173 | C175: 43199 | D175: ยอดยกมา17 | H175: TX10 | I175: 1607 | J175: =IF(D175<>"",VLOOKUP(H175,TABLEITEM,5,FALSE),"") -> EA | K175: 9 | L175: =IF(D175<>"",VLOOKUP(H175,TABLEITEM,2,FALSE),"") | M175: =IF(D175<>"",VLOOKUP(H175,TABLEITEM,3,FALSE),"") -> TERMINAL BLOCK TX10 | N175: =INSTOCK!$I175*INSTOCK!$K175 -> 14463
B176: 174 | C176: 43199 | D176: ยอดยกมา17 | H176: TXA1 | I176: 286 | J176: =IF(D176<>"",VLOOKUP(H176,TABLEITEM,5,FALSE),"") -> EA | K176: 5 | L176: =IF(D176<>"",VLOOKUP(H176,TABLEITEM,2,FALSE),"") | M176: =IF(D176<>"",VLOOKUP(H176,TABLEITEM,3,FALSE),"") -> END PLATE TXA1 | N176: =INSTOCK!$I176*INSTOCK!$K176 -> 1430
B177: 175 | C177: 43199 | D177: ยอดยกมา17 | H177: TX20 | I177: 630 | J177: =IF(D177<>"",VLOOKUP(H177,TABLEITEM,5,FALSE),"") -> EA | K177: 11.5 | L177: =IF(D177<>"",VLOOKUP(H177,TABLEITEM,2,FALSE),"") | M177: =IF(D177<>"",VLOOKUP(H177,TABLEITEM,3,FALSE),"") -> TERMINAL BLOCK TX20 | N177: =INSTOCK!$I177*INSTOCK!$K177 -> 7245
B178: 176 | C178: 43199 | D178: ยอดยกมา17 | H178: TX30 | I178: 336 | J178: =IF(D178<>"",VLOOKUP(H178,TABLEITEM,5,FALSE),"") -> EA | K178: 20 | L178: =IF(D178<>"",VLOOKUP(H178,TABLEITEM,2,FALSE),"") | M178: =IF(D178<>"",VLOOKUP(H178,TABLEITEM,3,FALSE),"") -> TERMINAL BLOCK TX30 | N178: =INSTOCK!$I178*INSTOCK!$K178 -> 6720
B179: 177 | C179: 43199 | D179: ยอดยกมา17 | H179: TXA3 | I179: 146 | J179: =IF(D179<>"",VLOOKUP(H179,TABLEITEM,5,FALSE),"") -> EA | K179: 6.86 | L179: =IF(D179<>"",VLOOKUP(H179,TABLEITEM,2,FALSE),"") | M179: =IF(D179<>"",VLOOKUP(H179,TABLEITEM,3,FALSE),"") -> END PLATE TXA3 | N179: =INSTOCK!$I179*INSTOCK!$K179 -> 1001.56
B180: 178 | C180: 43199 | D180: ยอดยกมา17 | H180: TX60 | I180: 186 | J180: =IF(D180<>"",VLOOKUP(H180,TABLEITEM,5,FALSE),"") -> EA | K180: 35 | L180: =IF(D180<>"",VLOOKUP(H180,TABLEITEM,2,FALSE),"") | M180: =IF(D180<>"",VLOOKUP(H180,TABLEITEM,3,FALSE),"") -> TERMINAL BLOCK TX60 | N180: =INSTOCK!$I180*INSTOCK!$K180 -> 6510
B181: 179 | C181: 43199 | D181: ยอดยกมา17 | H181: TXA6 | I181: 73 | J181: =IF(D181<>"",VLOOKUP(H181,TABLEITEM,5,FALSE),"") -> EA | K181: 8.8 | L181: =IF(D181<>"",VLOOKUP(H181,TABLEITEM,2,FALSE),"") | M181: =IF(D181<>"",VLOOKUP(H181,TABLEITEM,3,FALSE),"") -> END PLATE TXA6 | N181: =INSTOCK!$I181*INSTOCK!$K181 -> 642.4
B182: 180 | C182: 43199 | D182: ยอดยกมา17 | H182: TX100 | I182: 57 | J182: =IF(D182<>"",VLOOKUP(H182,TABLEITEM,5,FALSE),"") -> EA | K182: 75 | L182: =IF(D182<>"",VLOOKUP(H182,TABLEITEM,2,FALSE),"") | M182: =IF(D182<>"",VLOOKUP(H182,TABLEITEM,3,FALSE),"") -> TERMINAL BLOCK TX100 | N182: =INSTOCK!$I182*INSTOCK!$K182 -> 4275
B183: 181 | C183: 43199 | D183: ยอดยกมา17 | H183: TXA10 | I183: 83 | J183: =IF(D183<>"",VLOOKUP(H183,TABLEITEM,5,FALSE),"") -> EA | K183: 12 | L183: =IF(D183<>"",VLOOKUP(H183,TABLEITEM,2,FALSE),"") | M183: =IF(D183<>"",VLOOKUP(H183,TABLEITEM,3,FALSE),"") -> END PLATE TXA10 | N183: =INSTOCK!$I183*INSTOCK!$K183 -> 996
B184: 182 | C184: 43199 | D184: ยอดยกมา17 | H184: TX150 | I184: 25 | J184: =IF(D184<>"",VLOOKUP(H184,TABLEITEM,5,FALSE),"") -> EA | K184: 105 | L184: =IF(D184<>"",VLOOKUP(H184,TABLEITEM,2,FALSE),"") | M184: =IF(D184<>"",VLOOKUP(H184,TABLEITEM,3,FALSE),"") -> TERMINAL BLOCK TX150 | N184: =INSTOCK!$I184*INSTOCK!$K184 -> 2625
... B198: 196 | C198: 43199 | D198: ยอดยกมา17 | H198: RELAY | I198: 42 | J198: =IF(D198<>"",VLOOKUP(H198,TABLEITEM,5,FALSE),"") -> EA | K198: 117 | L198: =IF(D198<>"",VLOOKUP(H198,TABLEITEM,2,FALSE),"") | M198: =IF(D198<>"",VLOOKUP(H198,TABLEITEM,3,FALSE),"") -> รางรีเลย์ | N198: =INSTOCK!$I198*INSTOCK!$K198 -> 4914
B199: 197 | C199: 43199 | D199: ยอดยกมา17 | H199: UT-N2.5W | I199: 0 | J199: =IF(D199<>"",VLOOKUP(H199,TABLEITEM,5,FALSE),"") -> M | L199: =IF(D199<>"",VLOOKUP(H199,TABLEITEM,2,FALSE),"") | M199: =IF(D199<>"",VLOOKUP(H199,TABLEITEM,3,FALSE),"") -> TUEB 2.5 | N199: =INSTOCK!$I199*INSTOCK!$K199 -> 0
B200: 198 | C200: 43199 | D200: ยอดยกมา17 | H200: UT-N3.2W | I200: 600 | J200: =IF(D200<>"",VLOOKUP(H200,TABLEITEM,5,FALSE),"") -> M | K200: 4.95 | L200: =IF(D200<>"",VLOOKUP(H200,TABLEITEM,2,FALSE),"") | M200: =IF(D200<>"",VLOOKUP(H200,TABLEITEM,3,FALSE),"") -> TUEB 3.2 | N200: =INSTOCK!$I200*INSTOCK!$K200 -> 2970 | O200: 2200(55%)
B201: 199 | C201: 43199 | D201: ยอดยกมา17 | H201: UT-N3.6W | I201: 600 | J201: =IF(D201<>"",VLOOKUP(H201,TABLEITEM,5,FALSE),"") -> M | K201: 5.9175 | L201: =IF(D201<>"",VLOOKUP(H201,TABLEITEM,2,FALSE),"") | M201: =IF(D201<>"",VLOOKUP(H201,TABLEITEM,3,FALSE),"") -> TUBE 3.6 | N201: =INSTOCK!$I201*INSTOCK!$K201 -> 3550.5 | O201: 2630(55%)
B202: 200 | C202: 43199 | D202: ยอดยกมา17 | H202: UT-N4.2W | I202: 400 | J202: =IF(D202<>"",VLOOKUP(H202,TABLEITEM,5,FALSE),"") -> M | K202: 6.93 | L202: =IF(D202<>"",VLOOKUP(H202,TABLEITEM,2,FALSE),"") | M202: =IF(D202<>"",VLOOKUP(H202,TABLEITEM,3,FALSE),"") -> TUEB 4.2 | N202: =INSTOCK!$I202*INSTOCK!$K202 -> 2772 | O202: 3080(55%)
B203: 201 | C203: 43199 | D203: ยอดยกมา17 | H203: UT-N5.2W | I203: 200 | J203: =IF(D203<>"",VLOOKUP(H203,TABLEITEM,5,FALSE),"") -> M | K203: 10.53 | L203: =IF(D203<>"",VLOOKUP(H203,TABLEITEM,2,FALSE),"") | M203: =IF(D203<>"",VLOOKUP(H203,TABLEITEM,3,FALSE),"") -> TUEB 5.2 | N203: =INSTOCK!$I203*INSTOCK!$K203 -> 2106 | O203: 2340(55%)
B204: 202 | C204: 43199 | D204: ยอดยกมา17 | H204: CR-07P | I204: 300 | J204: =IF(D204<>"",VLOOKUP(H204,TABLEITEM,5,FALSE),"") -> M | K204: 12 | L204: =IF(D204<>"",VLOOKUP(H204,TABLEITEM,2,FALSE),"") | M204: =IF(D204<>"",VLOOKUP(H204,TABLEITEM,3,FALSE),"") -> ท่ออ่อนลูกฟูกชิดผ่า/ท่อผ่าดำ 7มิล | N204: =INSTOCK!$I204*INSTOCK!$K204 -> 3600
B205: 203 | C205: 43199 | D205: ยอดยกมา17 | H205: CR-011P | I205: 200 | J205: =IF(D205<>"",VLOOKUP(H205,TABLEITEM,5,FALSE),"") -> M | K205: 15 | L205: =IF(D205<>"",VLOOKUP(H205,TABLEITEM,2,FALSE),"") | M205: =IF(D205<>"",VLOOKUP(H205,TABLEITEM,3,FALSE),"") -> ท่ออ่อนลูกฟูกชิดผ่า/ท่อผ่าดำ 11มิล | N205: =INSTOCK!$I205*INSTOCK!$K205 -> 3000
...

Sheet TABLEITEM
A1: INSTOCK
A2: NO. | B2: CODE | C2: GROUP | D2: LIST | E2: BRAND | F2: unit | G2: MAX | H2: SUM IN | I2: SUM OUT | J2: คงเหลือ | L2: GROUP | M2: กลุ่ม ประเภท
A3: 304 | B3: HP-30 | D3: โฮปลั๊ก 30 มิล | E3: BANDEX | F3: EA | G3: =MAX(IF(INSTOCK!$H$3:$H$6125=B3,INSTOCK!$K$3:$K$6125)) -> 0 | H3: {=SUM(IF(INSTOCK!$H$3:$H$6125=B3,INSTOCK!$I$3:$I$6125))} -> 52 | I3: =SUM(IF([3]!Table13[ID]=B3,[3]!Table13[QTY])) -> #ERROR! | J3: =TABLEITEM!$H$3:$H$2749-TABLEITEM!$I$3:$I$2749 -> #ERROR! | L3: Busbar | M3: บัสบาร์
A4: 303 | B4: HP-25 | D4: โฮปลั๊ก 25 มิล | E4: BANDEX | F4: EA | G4: {=MAX(IF(INSTOCK!$H$3:$H$6125=B4,INSTOCK!$K$3:$K$6125))} -> 0 | H4: {=SUM(IF(INSTOCK!$H$3:$H$6125=B4,INSTOCK!$I$3:$I$6125))} -> 70 | I4: =ARRAY_CONSTRAIN(ARRAYFORMULA(SUM(IF([3]!Table13[ID]=B4,[3]!Table13[QTY]))), 1, 1) -> #ERROR! | J4: =TABLEITEM!$H$3:$H$2749-TABLEITEM!$I$3:$I$2749 -> #ERROR! | L4: wire | M4: สายไฟ
A5: 302 | B5: HP-22 | D5: โฮปลั๊ก 22 มิล | E5: BANDEX | F5: EA | G5: {=MAX(IF(INSTOCK!$H$3:$H$6125=B5,INSTOCK!$K$3:$K$6125))} -> 0 | H5: {=SUM(IF(INSTOCK!$H$3:$H$6125=B5,INSTOCK!$I$3:$I$6125))} -> 76 | I5: =ARRAY_CONSTRAIN(ARRAYFORMULA(SUM(IF([3]!Table13[ID]=B5,[3]!Table13[QTY]))), 1, 1) -> #ERROR! | J5: =TABLEITEM!$H$3:$H$2749-TABLEITEM!$I$3:$I$2749 -> #ERROR! | L5: ACC | M5: ชิ้นส่วน
A6: 301 | B6: HP-10 | D6: โฮปลั๊ก 10 มิล | E6: BANDEX | F6: EA | G6: {=MAX(IF(INSTOCK!$H$3:$H$6125=B6,INSTOCK!$K$3:$K$6125))} -> 0.81965 | H6: {=SUM(IF(INSTOCK!$H$3:$H$6125=B6,INSTOCK!$I$3:$I$6125))} -> 200 | I6: =ARRAY_CONSTRAIN(ARRAYFORMULA(SUM(IF([3]!Table13[ID]=B6,[3]!Table13[QTY]))), 1, 1) -> #ERROR! | J6: =TABLEITEM!$H$3:$H$2749-TABLEITEM!$I$3:$I$2749 -> #ERROR! | L6: Support | M6: ลูกถ้วย&Support
B7: HEATER-CS-600 | D7: ฮิตเตอร์อินฟราเรด CS-600MM 1000W AC220V | E7: แสงชัย | F7: EA | G7: {=MAX(IF(INSTOCK!$H$3:$H$6125=B7,INSTOCK!$K$3:$K$6125))} -> 901 | H7: {=SUM(IF(INSTOCK!$H$3:$H$6125=B7,INSTOCK!$I$3:$I$6125))} -> 2 | I7: =ARRAY_CONSTRAIN(ARRAYFORMULA(SUM(IF([3]!Table13[ID]=B7,[3]!Table13[QTY]))), 1, 1) -> #ERROR! | J7: =TABLEITEM!$H$3:$H$2749-TABLEITEM!$I$3:$I$2749 -> #ERROR! | L7: Key | M7: กุญแจ
B8: TH-T18 3.6A | D8: โอเวอร์โหลด TH-T18 3.6A | E8: MITSU | F8: EA | G8: {=MAX(IF(INSTOCK!$H$3:$H$6125=B8,INSTOCK!$K$3:$K$6125))} -> 310 | H8: {=SUM(IF(INSTOCK!$H$3:$H$6125=B8,INSTOCK!$I$3:$I$6125))} -> 2 | I8: =ARRAY_CONSTRAIN(ARRAYFORMULA(SUM(IF([3]!Table13[ID]=B8,[3]!Table13[QTY]))), 1, 1) -> #ERROR! | J8: =TABLEITEM!$H$3:$H$2749-TABLEITEM!$I$3:$I$2749 -> #ERROR! | L8: KG. | M8: กิโลกรัม
B9: TH-T18 2.1A | D9: โอเวอร์โหลด TH-T18 2.1A | E9: MITSU | F9: EA | G9: {=MAX(IF(INSTOCK!$H$3:$H$6125=B9,INSTOCK!$K$3:$K$6125))} -> 310 | H9: {=SUM(IF(INSTOCK!$H$3:$H$6125=B9,INSTOCK!$I$3:$I$6125))} -> 3 | I9: =ARRAY_CONSTRAIN(ARRAYFORMULA(SUM(IF([3]!Table13[ID]=B9,[3]!Table13[QTY]))), 1, 1) -> #ERROR! | J9: =TABLEITEM!$H$3:$H$2749-TABLEITEM!$I$3:$I$2749 -> #ERROR!
A10: 161 | B10: ALCOHOL | D10: แอลกอฮอลดีพิเศษ | E10: ตะวัน | F10: กล. | G10: {=MAX(IF(INSTOCK!$H$3:$H$6125=B10,INSTOCK!$K$3:$K$6125))} -> 260 | H10: {=SUM(IF(INSTOCK!$H$3:$H$6125=B10,INSTOCK!$I$3:$I$6125))} -> 21 | I10: =ARRAY_CONSTRAIN(ARRAYFORMULA(SUM(IF([3]!Table13[ID]=B10,[3]!Table13[QTY]))), 1, 1) -> #ERROR! | J10: =TABLEITEM!$H$3:$H$2749-TABLEITEM!$I$3:$I$2749 -> #ERROR!
B11: ACC-อิฐตัวหนอน | D11: อิฐตัวหนอนแดง | F11: EA | G11: {=MAX(IF(INSTOCK!$H$3:$H$6125=B11,INSTOCK!$K$3:$K$6125))} -> 7.5 | H11: {=SUM(IF(INSTOCK!$H$3:$H$6125=B11,INSTOCK!$I$3:$I$6125))} -> 760 | I11: =ARRAY_CONSTRAIN(ARRAYFORMULA(SUM(IF([3]!Table13[ID]=B11,[3]!Table13[QTY]))), 1, 1) -> #ERROR! | J11: =TABLEITEM!$H$3:$H$2749-TABLEITEM!$I$3:$I$2749 -> #ERROR!
B12: AR6Q | D12: อาร์กอน ขนาด 6คิว | E12: UIG | F12: ท่อ | G12: {=MAX(IF(INSTOCK!$H$3:$H$6125=B12,INSTOCK!$K$3:$K$6125))} -> 600 | H12: {=SUM(IF(INSTOCK!$H$3:$H$6125=B12,INSTOCK!$I$3:$I$6125))} -> 142 | I12: =ARRAY_CONSTRAIN(ARRAYFORMULA(SUM(IF([3]!Table13[ID]=B12,[3]!Table13[QTY]))), 1, 1) -> #ERROR! | J12: =TABLEITEM!$H$3:$H$2749-TABLEITEM!$I$3:$I$2749 -> #ERROR!
B13: UVTNA250 | D13: อันเดอร์โวลเตจ UVTNA250-05SVR FOR NF32-SV-250-SV ขวา AC200-250V | E13: MITSU | F13: EA | G13: {=MAX(IF(INSTOCK!$H$3:$H$6125=B13,INSTOCK!$K$3:$K$6125))} -> 3103.65 | H13: {=SUM(IF(INSTOCK!$H$3:$H$6125=B13,INSTOCK!$I$3:$I$6125))} -> 1 | I13: =ARRAY_CONSTRAIN(ARRAYFORMULA(SUM(IF([3]!Table13[ID]=B13,[3]!Table13[QTY]))), 1, 1) -> #ERROR! | J13: =TABLEITEM!$H$3:$H$2749-TABLEITEM!$I$3:$I$2749 -> #ERROR!
B14: OFFICE-0000040 | D14: อะไหล่ม๊อบเพาเวอร์ BLACK MAN 10" | F14: EA | G14: {=MAX(IF(INSTOCK!$H$3:$H$6125=B14,INSTOCK!$K$3:$K$6125))} -> 95 | H14: {=SUM(IF(INSTOCK!$H$3:$H$6125=B14,INSTOCK!$I$3:$I$6125))} -> 1 | I14: =ARRAY_CONSTRAIN(ARRAYFORMULA(SUM(IF([3]!Table13[ID]=B14,[3]!Table13[QTY]))), 1, 1) -> #ERROR! | J14: =TABLEITEM!$H$3:$H$2749-TABLEITEM!$I$3:$I$2749 -> #ERROR!
B15: OFFICE-0003063 | D15: ไม้กวาดไนล่อน 35ซม. ด้ามยาว 120 ซม. | E15: NCL | F15: EA | G15: {=MAX(IF(INSTOCK!$H$3:$H$6125=B15,INSTOCK!$K$3:$K$6125))} -> 135.51 | H15: {=SUM(IF(INSTOCK!$H$3:$H$6125=B15,INSTOCK!$I$3:$I$6125))} -> 6 | I15: =ARRAY_CONSTRAIN(ARRAYFORMULA(SUM(IF([3]!Table13[ID]=B15,[3]!Table13[QTY]))), 1, 1) -> #ERROR! | J15: =TABLEITEM!$H$3:$H$2749-TABLEITEM!$I$3:$I$2749 -> #ERROR!
B16: TAP-4229 | D16: อะคริลิคโฟมเทป 12mmx10M #4229 | E16: 3M | F16: EA | G16: {=MAX(IF(INSTOCK!$H$3:$H$6125=B16,INSTOCK!$K$3:$K$6125))} -> 150 | H16: {=SUM(IF(INSTOCK!$H$3:$H$6125=B16,INSTOCK!$I$3:$I$6125))} -> 75 | I16: =ARRAY_CONSTRAIN(ARRAYFORMULA(SUM(IF([3]!Table13[ID]=B16,[3]!Table13[QTY]))), 1, 1) -> #ERROR! | J16: =TABLEITEM!$H$3:$H$2749-TABLEITEM!$I$3:$I$2749 -> #ERROR!
B17: TS2BIL2 | D17: ออดชนิดเสียงดังไม่ต่อเนื่องมีแลมป์ LED | E17: ธีรชัย | F17: EA | G17: {=MAX(IF(INSTOCK!$H$3:$H$6125=B17,INSTOCK!$K$3:$K$6125))} -> 14972 | H17: {=SUM(IF(INSTOCK!$H$3:$H$6125=B17,INSTOCK!$I$3:$I$6125))} -> 8 | I17: =ARRAY_CONSTRAIN(ARRAYFORMULA(SUM(IF([3]!Table13[ID]=B17,[3]!Table13[QTY]))), 1, 1) -> #ERROR! | J17: =TABLEITEM!$H$3:$H$2749-TABLEITEM!$I$3:$I$2749 -> #ERROR!
B18: OL148 | D18: ออกซิเจนเหลว ขนาด 148 คิว | E18: UIG | F18: ท่อ | G18: {=MAX(IF(INSTOCK!$H$3:$H$6125=B18,INSTOCK!$K$3:$K$6125))} -> 2960 | H18: {=SUM(IF(INSTOCK!$H$3:$H$6125=B18,INSTOCK!$I$3:$I$6125))} -> 29 | I18: =ARRAY_CONSTRAIN(ARRAYFORMULA(SUM(IF([3]!Table13[ID]=B18,[3]!Table13[QTY]))), 1, 1) -> #ERROR! | J18: =TABLEITEM!$H$3:$H$2749-TABLEITEM!$I$3:$I$2749 -> #ERROR!
B19: AT | D19: อแดปเตอร์ต่อสลัก | F19: EA | G19: {=MAX(IF(INSTOCK!$H$3:$H$6125=B19,INSTOCK!$K$3:$K$6125))} -> 0 | H19: {=SUM(IF(INSTOCK!$H$3:$H$6125=B19,INSTOCK!$I$3:$I$6125))} -> 0 | I19: =ARRAY_CONSTRAIN(ARRAYFORMULA(SUM(IF([3]!Table13[ID]=B19,[3]!Table13[QTY]))), 1, 1) -> #ERROR! | J19: =TABLEITEM!$H$3:$H$2749-TABLEITEM!$I$3:$I$2749 -> #ERROR!
B20: DP8SUS | D20: แหวนอีแปะ สแตนเลส M8 | E20: KM | F20: EA | G20: {=MAX(IF(INSTOCK!$H$3:$H$6125=B20,INSTOCK!$K$3:$K$6125))} -> 0.385 | H20: {=SUM(IF(INSTOCK!$H$3:$H$6125=B20,INSTOCK!$I$3:$I$6125))} -> 3000 | I20: =ARRAY_CONSTRAIN(ARRAYFORMULA(SUM(IF([3]!Table13[ID]=B20,[3]!Table13[QTY]))), 1, 1) -> #ERROR! | J20: =TABLEITEM!$H$3:$H$2749-TABLEITEM!$I$3:$I$2749 -> #ERROR!
B21: DP6SUS | D21: แหวนอีแปะ สแตนเลส M6 | E21: KM | F21: EA | G21: {=MAX(IF(INSTOCK!$H$3:$H$6125=B21,INSTOCK!$K$3:$K$6125))} -> 0.25 | H21: {=SUM(IF(INSTOCK!$H$3:$H$6125=B21,INSTOCK!$I$3:$I$6125))} -> 13000 | I21: =ARRAY_CONSTRAIN(ARRAYFORMULA(SUM(IF([3]!Table13[ID]=B21,[3]!Table13[QTY]))), 1, 1) -> #ERROR! | J21: =TABLEITEM!$H$3:$H$2749-TABLEITEM!$I$3:$I$2749 -> #ERROR!
B22: DP5SUS | D22: แหวนอีแปะ สแตนเลส M5 | E22: KM | F22: EA | G22: {=MAX(IF(INSTOCK!$H$3:$H$6125=B22,INSTOCK!$K$3:$K$6125))} -> 0.225 | H22: {=SUM(IF(INSTOCK!$H$3:$H$6125=B22,INSTOCK!$I$3:$I$6125))} -> 1000 | I22: =ARRAY_CONSTRAIN(ARRAYFORMULA(SUM(IF([3]!Table13[ID]=B22,[3]!Table13[QTY]))), 1, 1) -> #ERROR! | J22: =TABLEITEM!$H$3:$H$2749-TABLEITEM!$I$3:$I$2749 -> #ERROR!
B23: DP4SUS | D23: แหวนอีแปะ สแตนเลส M4 | E23: KM | F23: EA | G23: {=MAX(IF(INSTOCK!$H$3:$H$6125=B23,INSTOCK!$K$3:$K$6125))} -> 0 | H23: {=SUM(IF(INSTOCK!$H$3:$H$6125=B23,INSTOCK!$I$3:$I$6125))} -> 0 | I23: =ARRAY_CONSTRAIN(ARRAYFORMULA(SUM(IF([3]!Table13[ID]=B23,[3]!Table13[QTY]))), 1, 1) -> #ERROR! | J23: =TABLEITEM!$H$3:$H$2749-TABLEITEM!$I$3:$I$2749 -> #ERROR!
B24: DP10SUS | D24: แหวนอีแปะ SUS M10 | E24: AS | F24: EA | G24: {=MAX(IF(INSTOCK!$H$3:$H$6125=B24,INSTOCK!$K$3:$K$6125))} -> 2 | H24: {=SUM(IF(INSTOCK!$H$3:$H$6125=B24,INSTOCK!$I$3:$I$6125))} -> 360 | I24: =ARRAY_CONSTRAIN(ARRAYFORMULA(SUM(IF([3]!Table13[ID]=B24,[3]!Table13[QTY]))), 1, 1) -> #ERROR! | J24: =TABLEITEM!$H$3:$H$2749-TABLEITEM!$I$3:$I$2749 -> #ERROR!
B25: DP8 | D25: แหวนอีแปะ M8 ชุบขาว | E25: KM | F25: EA | G25: {=MAX(IF(INSTOCK!$H$3:$H$6125=B25,INSTOCK!$K$3:$K$6125))} -> 1.09 | H25: {=SUM(IF(INSTOCK!$H$3:$H$6125=B25,INSTOCK!$I$3:$I$6125))} -> 420000 | I25: =ARRAY_CONSTRAIN(ARRAYFORMULA(SUM(IF([3]!Table13[ID]=B25,[3]!Table13[QTY]))), 1, 1) -> #ERROR! | J25: =TABLEITEM!$H$3:$H$2749-TABLEITEM!$I$3:$I$2749 -> #ERROR!
B26: DP8HDG | D26: แหวนอีแปะ M8 HDG | E26: KM | F26: EA | G26: {=MAX(IF(INSTOCK!$H$3:$H$6125=B26,INSTOCK!$K$3:$K$6125))} -> 0.39 | H26: {=SUM(IF(INSTOCK!$H$3:$H$6125=B26,INSTOCK!$I$3:$I$6125))} -> 14000 | I26: =ARRAY_CONSTRAIN(ARRAYFORMULA(SUM(IF([3]!Table13[ID]=B26,[3]!Table13[QTY]))), 1, 1) -> #ERROR! | J26: =TABLEITEM!$H$3:$H$2749-TABLEITEM!$I$3:$I$2749 -> #ERROR!
B27: DP6 | D27: แหวนอีแปะ M6 ชุบขาว | E27: KM | F27: EA | G27: {=MAX(IF(INSTOCK!$H$3:$H$6125=B27,INSTOCK!$K$3:$K$6125))} -> 0.125 | H27: {=SUM(IF(INSTOCK!$H$3:$H$6125=B27,INSTOCK!$I$3:$I$6125))} -> 45000 | I27: =ARRAY_CONSTRAIN(ARRAYFORMULA(SUM(IF([3]!Table13[ID]=B27,[3]!Table13[QTY]))), 1, 1) -> #ERROR! | J27: =TABLEITEM!$H$3:$H$2749-TABLEITEM!$I$3:$I$2749 -> #ERROR!
B28: DP5Z | D28: แหวนอีแปะ M5 ชุบขาว | E28: KM | F28: EA | G28: {=MAX(IF(INSTOCK!$H$3:$H$6125=B28,INSTOCK!$K$3:$K$6125))} -> 0.055 | H28: {=SUM(IF(INSTOCK!$H$3:$H$6125=B28,INSTOCK!$I$3:$I$6125))} -> 2000 | I28: =ARRAY_CONSTRAIN(ARRAYFORMULA(SUM(IF([3]!Table13[ID]=B28,[3]!Table13[QTY]))), 1, 1) -> #ERROR! | J28: =TABLEITEM!$H$3:$H$2749-TABLEITEM!$I$3:$I$2749 -> #ERROR!
B29: DP4Z | D29: แหวนอีแปะ M4 ชุบขาว | E29: KM | F29: EA | G29: {=MAX(IF(INSTOCK!$H$3:$H$6125=B29,INSTOCK!$K$3:$K$6125))} -> 0.13 | H29: {=SUM(IF(INSTOCK!$H$3:$H$6125=B29,INSTOCK!$I$3:$I$6125))} -> 22000 | I29: =ARRAY_CONSTRAIN(ARRAYFORMULA(SUM(IF([3]!Table13[ID]=B29,[3]!Table13[QTY]))), 1, 1) -> #ERROR! | J29: =TABLEITEM!$H$3:$H$2749-TABLEITEM!$I$3:$I$2749 -> #ERROR!
B30: DP3Z | D30: แหวนอีแปะ M3 ชุบขาว | E30: KM | F30: EA | G30: {=MAX(IF(INSTOCK!$H$3:$H$6125=B30,INSTOCK!$K$3:$K$6125))} -> 0 | H30: {=SUM(IF(INSTOCK!$H$3:$H$6125=B30,INSTOCK!$I$3:$I$6125))} -> 0 | I30: =ARRAY_CONSTRAIN(ARRAYFORMULA(SUM(IF([3]!Table13[ID]=B30,[3]!Table13[QTY]))), 1, 1) -> #ERROR! | J30: =TABLEITEM!$H$3:$H$2749-TABLEITEM!$I$3:$I$2749 -> #ERROR!
B31: DP16 | D31: แหวนอีแปะ M16 ชุบขาว | E31: KM | F31: EA | G31: {=MAX(IF(INSTOCK!$H$3:$H$6125=B31,INSTOCK!$K$3:$K$6125))} -> 0.84 | H31: {=SUM(IF(INSTOCK!$H$3:$H$6125=B31,INSTOCK!$I$3:$I$6125))} -> 2400 | I31: =ARRAY_CONSTRAIN(ARRAYFORMULA(SUM(IF([3]!Table13[ID]=B31,[3]!Table13[QTY]))), 1, 1) -> #ERROR! | J31: =TABLEITEM!$H$3:$H$2749-TABLEITEM!$I$3:$I$2749 -> #ERROR!
... B59: PN4 | D59: แหวนพลาสติก M4 | E59: TPC | F59: EA | G59: {=MAX(IF(INSTOCK!$H$3:$H$6125=B59,INSTOCK!$K$3:$K$6125))} -> 0.6 | H59: {=SUM(IF(INSTOCK!$H$3:$H$6125=B59,INSTOCK!$I$3:$I$6125))} -> 1000 | I59: =ARRAY_CONSTRAIN(ARRAYFORMULA(SUM(IF([3]!Table13[ID]=B59,[3]!Table13[QTY]))), 1, 1) -> #ERROR! | J59: =TABLEITEM!$H$3:$H$2749-TABLEITEM!$I$3:$I$2749 -> #ERROR!
B60: MCW 8 | D60: แหวนฉิ่ง M8 | E60: GROWERMETAL | F60: EA | G60: =MAX(IF(INSTOCK!$H$3:$H$6125=B60,INSTOCK!$K$3:$K$6125)) -> 0 | H60: {=SUM(IF(INSTOCK!$H$3:$H$6125=B60,INSTOCK!$I$3:$I$6125))} -> 80000 | I60: =ARRAY_CONSTRAIN(ARRAYFORMULA(SUM(IF([3]!Table13[ID]=B60,[3]!Table13[QTY]))), 1, 1) -> #ERROR! | J60: =TABLEITEM!$H$3:$H$2749-TABLEITEM!$I$3:$I$2749 -> #ERROR!
B61: MCW 6 | D61: แหวนฉิ่ง M6 | E61: GROWERMETAL | F61: EA | G61: {=MAX(IF(INSTOCK!$H$3:$H$6125=B61,INSTOCK!$K$3:$K$6125))} -> 0.6 | H61: {=SUM(IF(INSTOCK!$H$3:$H$6125=B61,INSTOCK!$I$3:$I$6125))} -> 80000 | I61: =ARRAY_CONSTRAIN(ARRAYFORMULA(SUM(IF([3]!Table13[ID]=B61,[3]!Table13[QTY]))), 1, 1) -> #ERROR! | J61: =TABLEITEM!$H$3:$H$2749-TABLEITEM!$I$3:$I$2749 -> #ERROR!
B62: MCW 12 | D62: แหวนฉิ่ง M12 | E62: GROWERMETAL | F62: EA | G62: {=MAX(IF(INSTOCK!$H$3:$H$6125=B62,INSTOCK!$K$3:$K$6125))} -> 2.7 | H62: {=SUM(IF(INSTOCK!$H$3:$H$6125=B62,INSTOCK!$I$3:$I$6125))} -> 80000 | I62: =ARRAY_CONSTRAIN(ARRAYFORMULA(SUM(IF([3]!Table13[ID]=B62,[3]!Table13[QTY]))), 1, 1) -> #ERROR! | J62: =TABLEITEM!$H$3:$H$2749-TABLEITEM!$I$3:$I$2749 -> #ERROR!
B63: MCW 10 | D63: แหวนฉิ่ง M10 | E63: GROWERMETAL | F63: EA | G63: {=MAX(IF(INSTOCK!$H$3:$H$6125=B63,INSTOCK!$K$3:$K$6125))} -> 1.6 | H63: {=SUM(IF(INSTOCK!$H$3:$H$6125=B63,INSTOCK!$I$3:$I$6125))} -> 80000 | I63: =ARRAY_CONSTRAIN(ARRAYFORMULA(SUM(IF([3]!Table13[ID]=B63,[3]!Table13[QTY]))), 1, 1) -> #ERROR! | J63: =TABLEITEM!$H$3:$H$2749-TABLEITEM!$I$3:$I$2749 -> #ERROR!
B64: SRST6 | D64: แหวนจักร M6 | E64: KM | F64: EA | G64: {=MAX(IF(INSTOCK!$H$3:$H$6125=B64,INSTOCK!$K$3:$K$6125))} -> 0.19 | H64: {=SUM(IF(INSTOCK!$H$3:$H$6125=B64,INSTOCK!$I$3:$I$6125))} -> 6000 | I64: =ARRAY_CONSTRAIN(ARRAYFORMULA(SUM(IF([3]!Table13[ID]=B64,[3]!Table13[QTY]))), 1, 1) -> #ERROR! | J64: =TABLEITEM!$H$3:$H$2749-TABLEITEM!$I$3:$I$2749 -> #ERROR!
B65: ACC-หินเกล็ด | D65: หินเกล็ด ใหญ่ | F65: EA | G65: {=MAX(IF(INSTOCK!$H$3:$H$6125=B65,INSTOCK!$K$3:$K$6125))} -> 3000 | H65: {=SUM(IF(INSTOCK!$H$3:$H$6125=B65,INSTOCK!$I$3:$I$6125))} -> 1 | I65: =ARRAY_CONSTRAIN(ARRAYFORMULA(SUM(IF([3]!Table13[ID]=B65,[3]!Table13[QTY]))), 1, 1) -> #ERROR! | J65: =TABLEITEM!$H$3:$H$2749-TABLEITEM!$I$3:$I$2749 -> #ERROR!
A66: 453 | B66: 218-FB | D66: หางปลาหัวเสียบก้านไม้ขีด 218-FD สีน้ำเงิน | E66: T.LUG | F66: EA | G66: {=MAX(IF(INSTOCK!$H$3:$H$6125=B66,INSTOCK!$K$3:$K$6125))} -> 3.25 | H66: {=SUM(IF(INSTOCK!$H$3:$H$6125=B66,INSTOCK!$I$3:$I$6125))} -> 1000 | I66: =ARRAY_CONSTRAIN(ARRAYFORMULA(SUM(IF([3]!Table13[ID]=B66,[3]!Table13[QTY]))), 1, 1) -> #ERROR! | J66: =TABLEITEM!$H$3:$H$2749-TABLEITEM!$I$3:$I$2749 -> #ERROR!
A67: 459 | B67: KT22-16 | D67: หางปลาเสียบแบนสีแดง KT22-16 | E67: T.LUG | F67: EA | G67: {=MAX(IF(INSTOCK!$H$3:$H$6125=B67,INSTOCK!$K$3:$K$6125))} -> 0 | H67: {=SUM(IF(INSTOCK!$H$3:$H$6125=B67,INSTOCK!$I$3:$I$6125))} -> 900 | I67: =ARRAY_CONSTRAIN(ARRAYFORMULA(SUM(IF([3]!Table13[ID]=B67,[3]!Table13[QTY]))), 1, 1) -> #ERROR! | J67: =TABLEITEM!$H$3:$H$2749-TABLEITEM!$I$3:$I$2749 -> #ERROR!
A68: 454 | B68: F2.5-A | D68: หางปลาเสียบตัวเมียชนิดหุ้ม F2.5-A | E68: T.LUG | F68: EA | G68: {=MAX(IF(INSTOCK!$H$3:$H$6125=B68,INSTOCK!$K$3:$K$6125))} -> 2.5 | H68: {=SUM(IF(INSTOCK!$H$3:$H$6125=B68,INSTOCK!$I$3:$I$6125))} -> 1000 | I68: =ARRAY_CONSTRAIN(ARRAYFORMULA(SUM(IF([3]!Table13[ID]=B68,[3]!Table13[QTY]))), 1, 1) -> #ERROR! | J68: =TABLEITEM!$H$3:$H$2749-TABLEITEM!$I$3:$I$2749 -> #ERROR!
A69: 455 | B69: F2.5-B | D69: หางปลาเสียบตัวผู้ชนิดหุ้ม F2.5-B | E69: T.LUG | F69: EA | G69: {=MAX(IF(INSTOCK!$H$3:$H$6125=B69,INSTOCK!$K$3:$K$6125))} -> 2.5 | H69: {=SUM(IF(INSTOCK!$H$3:$H$6125=B69,INSTOCK!$I$3:$I$6125))} -> 1145 | I69: =ARRAY_CONSTRAIN(ARRAYFORMULA(SUM(IF([3]!Table13[ID]=B69,[3]!Table13[QTY]))), 1, 1) -> #ERROR! | J69: =TABLEITEM!$H$3:$H$2749-TABLEITEM!$I$3:$I$2749 -> #ERROR!
A70: 456 | B70: F1.5-B | D70: หางปลาเสียบตัวผู้ชนิดหุ้ม F1.5-B | E70: T.LUG | F70: EA | G70: {=MAX(IF(INSTOCK!$H$3:$H$6125=B70,INSTOCK!$K$3:$K$6125))} -> 2.1 | H70: {=SUM(IF(INSTOCK!$H$3:$H$6125=B70,INSTOCK!$I$3:$I$6125))} -> 249 | I70: =ARRAY_CONSTRAIN(ARRAYFORMULA(SUM(IF([3]!Table13[ID]=B70,[3]!Table13[QTY]))), 1, 1) -> #ERROR! | J70: =TABLEITEM!$H$3:$H$2749-TABLEITEM!$I$3:$I$2749 -> #ERROR!
A71: 465 | B71: 518-FB | D71: หางปลาเสียบก้านไม้ขีด 518-FBเหลือง | E71: T.LUG | F71: EA | G71: {=MAX(IF(INSTOCK!$H$3:$H$6125=B71,INSTOCK!$K$3:$K$6125))} -> 6 | H71: {=SUM(IF(INSTOCK!$H$3:$H$6125=B71,INSTOCK!$I$3:$I$6125))} -> 1000 | I71: =ARRAY_CONSTRAIN(ARRAYFORMULA(SUM(IF([3]!Table13[ID]=B71,[3]!Table13[QTY]))), 1, 1) -> #ERROR! | J71: =TABLEITEM!$H$3:$H$2749-TABLEITEM!$I$3:$I$2749 -> #ERROR!
A72: 464 | B72: 510-FB | D72: หางปลาเสียบก้านไม้ขีด 510-FBเหลือง | E72: T.LUG | F72: EA | G72: {=MAX(IF(INSTOCK!$H$3:$H$6125=B72,INSTOCK!$K$3:$K$6125))} -> 5.25 | H72: {=SUM(IF(INSTOCK!$H$3:$H$6125=B72,INSTOCK!$I$3:$I$6125))} -> 400 | I72: =ARRAY_CONSTRAIN(ARRAYFORMULA(SUM(IF([3]!Table13[ID]=B72,[3]!Table13[QTY]))), 1, 1) -> #ERROR! | J72: =TABLEITEM!$H$3:$H$2749-TABLEITEM!$I$3:$I$2749 -> #ERROR!
A73: 457 | B73: V2.5-7A | D73: หางปลาไม้แบด V2.5-7Aสีน้ำเงิน | E73: T.LUG | F73: EA | G73: {=MAX(IF(INSTOCK!$H$3:$H$6125=B73,INSTOCK!$K$3:$K$6125))} -> 1.8 | H73: {=SUM(IF(INSTOCK!$H$3:$H$6125=B73,INSTOCK!$I$3:$I$6125))} -> 600 | I73: =ARRAY_CONSTRAIN(ARRAYFORMULA(SUM(IF([3]!Table13[ID]=B73,[3]!Table13[QTY]))), 1, 1) -> #ERROR! | J73: =TABLEITEM!$H$3:$H$2749-TABLEITEM!$I$3:$I$2749 -> #ERROR!
A74: 458 | B74: V1.5-7A | D74: หางปลาไม้แบด V1.5-7Aสีแดง | E74: T.LUG | F74: EA | G74: {=MAX(IF(INSTOCK!$H$3:$H$6125=B74,INSTOCK!$K$3:$K$6125))} -> 1.8 | H74: {=SUM(IF(INSTOCK!$H$3:$H$6125=B74,INSTOCK!$I$3:$I$6125))} -> 499 | I74: =ARRAY_CONSTRAIN(ARRAYFORMULA(SUM(IF([3]!Table13[ID]=B74,[3]!Table13[QTY]))), 1, 1) -> #ERROR! | J74: =TABLEITEM!$H$3:$H$2749-TABLEITEM!$I$3:$I$2749 -> #ERROR!
A75: 460 | B75: BF6 | D75: หางปลาต่อกลาง BF6 สีเหลือง | E75: T.LUG | F75: EA | G75: {=MAX(IF(INSTOCK!$H$3:$H$6125=B75,INSTOCK!$K$3:$K$6125))} -> 3.25 | H75: {=SUM(IF(INSTOCK!$H$3:$H$6125=B75,INSTOCK!$I$3:$I$6125))} -> 192 | I75: =ARRAY_CONSTRAIN(ARRAYFORMULA(SUM(IF([3]!Table13[ID]=B75,[3]!Table13[QTY]))), 1, 1) -> #ERROR! | J75: =TABLEITEM!$H$3:$H$2749-TABLEITEM!$I$3:$I$2749 -> #ERROR!
A76: 375 | B76: YF6-6 | D76: หางปลาแฉกหุ้ม 6-6 | E76: T.LUG | F76: EA | G76: {=MAX(IF(INSTOCK!$H$3:$H$6125=B76,INSTOCK!$K$3:$K$6125))} -> 3 | H76: {=SUM(IF(INSTOCK!$H$3:$H$6125=B76,INSTOCK!$I$3:$I$6125))} -> 178 | I76: =ARRAY_CONSTRAIN(ARRAYFORMULA(SUM(IF([3]!Table13[ID]=B76,[3]!Table13[QTY]))), 1, 1) -> #ERROR! | J76: =TABLEITEM!$H$3:$H$2749-TABLEITEM!$I$3:$I$2749 -> #ERROR!
A77: 374 | B77: YF6-5 | D77: หางปลาแฉกหุ้ม 6-5 | E77: T.LUG | F77: EA | G77: {=MAX(IF(INSTOCK!$H$3:$H$6125=B77,INSTOCK!$K$3:$K$6125))} -> 1.9 | H77: {=SUM(IF(INSTOCK!$H$3:$H$6125=B77,INSTOCK!$I$3:$I$6125))} -> 22 | I77: =ARRAY_CONSTRAIN(ARRAYFORMULA(SUM(IF([3]!Table13[ID]=B77,[3]!Table13[QTY]))), 1, 1) -> #ERROR! | J77: =TABLEITEM!$H$3:$H$2749-TABLEITEM!$I$3:$I$2749 -> #ERROR!
... A99: 384 | B99: RF6-10 | D99: หางปลากลมหุ้ม 6-10 | E99: T.LUG | F99: EA | G99: {=MAX(IF(INSTOCK!$H$3:$H$6125=B99,INSTOCK!$K$3:$K$6125))} -> 4.5 | H99: {=SUM(IF(INSTOCK!$H$3:$H$6125=B99,INSTOCK!$I$3:$I$6125))} -> 24 | I99: =ARRAY_CONSTRAIN(ARRAYFORMULA(SUM(IF([3]!Table13[ID]=B99,[3]!Table13[QTY]))), 1, 1) -> #ERROR! | J99: =TABLEITEM!$H$3:$H$2749-TABLEITEM!$I$3:$I$2749 -> #ERROR!
B100: RF5-12 | D100: หางปลากลมหุ้ม 5-12 | E100: TLUG | F100: EA | G100: {=MAX(IF(INSTOCK!$H$3:$H$6125=B100,INSTOCK!$K$3:$K$6125))} -> 0 | H100: {=SUM(IF(INSTOCK!$H$3:$H$6125=B100,INSTOCK!$I$3:$I$6125))} -> 0 | I100: =ARRAY_CONSTRAIN(ARRAYFORMULA(SUM(IF([3]!Table13[ID]=B100,[3]!Table13[QTY]))), 1, 1) -> #ERROR! | J100: =TABLEITEM!$H$3:$H$2749-TABLEITEM!$I$3:$I$2749 -> #ERROR!
A101: 380 | B101: RF5.5-10 | D101: หางปลากลมหุ้ม 5.5-10 | E101: T.LUG | F101: EA | G101: {=MAX(IF(INSTOCK!$H$3:$H$6125=B101,INSTOCK!$K$3:$K$6125))} -> 4.2 | H101: {=SUM(IF(INSTOCK!$H$3:$H$6125=B101,INSTOCK!$I$3:$I$6125))} -> 100 | I101: =ARRAY_CONSTRAIN(ARRAYFORMULA(SUM(IF([3]!Table13[ID]=B101,[3]!Table13[QTY]))), 1, 1) -> #ERROR! | J101: =TABLEITEM!$H$3:$H$2749-TABLEITEM!$I$3:$I$2749 -> #ERROR!
A102: 378 | B102: RF4-4 | D102: หางปลากลมหุ้ม 4-4 | E102: T.LUG | F102: EA | G102: {=MAX(IF(INSTOCK!$H$3:$H$6125=B102,INSTOCK!$K$3:$K$6125))} -> 2 | H102: {=SUM(IF(INSTOCK!$H$3:$H$6125=B102,INSTOCK!$I$3:$I$6125))} -> 149 | I102: =ARRAY_CONSTRAIN(ARRAYFORMULA(SUM(IF([3]!Table13[ID]=B102,[3]!Table13[QTY]))), 1, 1) -> #ERROR! | J102: =TABLEITEM!$H$3:$H$2749-TABLEITEM!$I$3:$I$2749 -> #ERROR!
A103: 377 | B103: RF2.5-5 | D103: หางปลากลมหุ้ม 2.5-5 | E103: T.LUG | F103: EA | G103: {=MAX(IF(INSTOCK!$H$3:$H$6125=B103,INSTOCK!$K$3:$K$6125))} -> 1.2 | H103: {=SUM(IF(INSTOCK!$H$3:$H$6125=B103,INSTOCK!$I$3:$I$6125))} -> 928 | I103: =ARRAY_CONSTRAIN(ARRAYFORMULA(SUM(IF([3]!Table13[ID]=B103,[3]!Table13[QTY]))), 1, 1) -> #ERROR! | J103: =TABLEITEM!$H$3:$H$2749-TABLEITEM!$I$3:$I$2749 -> #ERROR!
A104: 379 | B104: RF2.5-4 | D104: หางปลากลมหุ้ม 2.5-4 | E104: T.LUG | F104: EA | G104: {=MAX(IF(INSTOCK!$H$3:$H$6125=B104,INSTOCK!$K$3:$K$6125))} -> 1.2 | H104: {=SUM(IF(INSTOCK!$H$3:$H$6125=B104,INSTOCK!$I$3:$I$6125))} -> 610 | I104: =ARRAY_CONSTRAIN(ARRAYFORMULA(SUM(IF([3]!Table13[ID]=B104,[3]!Table13[QTY]))), 1, 1) -> #ERROR! | J104: =TABLEITEM!$H$3:$H$2749-TABLEITEM!$I$3:$I$2749 -> #ERROR!
A105: 376 | B105: RF1.5-3 | D105: หางปลากลมหุ้ม 1.5-3 | E105: T.LUG | F105: EA | G105: {=MAX(IF(INSTOCK!$H$3:$H$6125=B105,INSTOCK!$K$3:$K$6125))} -> 1.2 | H105: {=SUM(IF(INSTOCK!$H$3:$H$6125=B105,INSTOCK!$I$3:$I$6125))} -> 1600 | I105: =ARRAY_CONSTRAIN(ARRAYFORMULA(SUM(IF([3]!Table13[ID]=B105,[3]!Table13[QTY]))), 1, 1) -> #ERROR! | J105: =TABLEITEM!$H$3:$H$2749-TABLEITEM!$I$3:$I$2749 -> #ERROR!
A106: 420 | B106: PL25-8 | D106: หางปลากลมเปลือยหนา 25-8 | E106: LIB | F106: EA | G106: {=MAX(IF(INSTOCK!$H$3:$H$6125=B106,INSTOCK!$K$3:$K$6125))} -> 9 | H106: {=SUM(IF(INSTOCK!$H$3:$H$6125=B106,INSTOCK!$I$3:$I$6125))} -> 381 | I106: =ARRAY_CONSTRAIN(ARRAYFORMULA(SUM(IF([3]!Table13[ID]=B106,[3]!Table13[QTY]))), 1, 1) -> #ERROR! | J106: =TABLEITEM!$H$3:$H$2749-TABLEITEM!$I$3:$I$2749 -> #ERROR!
A107: 419 | B107: PL25-6 | D107: หางปลากลมเปลือยหนา 25-6 | E107: LIB | F107: EA | G107: {=MAX(IF(INSTOCK!$H$3:$H$6125=B107,INSTOCK!$K$3:$K$6125))} -> 9 | H107: {=SUM(IF(INSTOCK!$H$3:$H$6125=B107,INSTOCK!$I$3:$I$6125))} -> 452 | I107: =ARRAY_CONSTRAIN(ARRAYFORMULA(SUM(IF([3]!Table13[ID]=B107,[3]!Table13[QTY]))), 1, 1) -> #ERROR! | J107: =TABLEITEM!$H$3:$H$2749-TABLEITEM!$I$3:$I$2749 -> #ERROR!
A108: 421 | B108: PL25-10 | D108: หางปลากลมเปลือยหนา 25-10 | E108: LIB | F108: EA | G108: {=MAX(IF(INSTOCK!$H$3:$H$6125=B108,INSTOCK!$K$3:$K$6125))} -> 9 | H108: {=SUM(IF(INSTOCK!$H$3:$H$6125=B108,INSTOCK!$I$3:$I$6125))} -> 210 | I108: =ARRAY_CONSTRAIN(ARRAYFORMULA(SUM(IF([3]!Table13[ID]=B108,[3]!Table13[QTY]))), 1, 1) -> #ERROR! | J108: =TABLEITEM!$H$3:$H$2749-TABLEITEM!$I$3:$I$2749 -> #ERROR!
A109: 418 | B109: PL16-8 | D109: หางปลากลมเปลือยหนา 16-8 | E109: LIB | F109: EA | G109: {=MAX(IF(INSTOCK!$H$3:$H$6125=B109,INSTOCK!$K$3:$K$6125))} -> 6 | H109: {=SUM(IF(INSTOCK!$H$3:$H$6125=B109,INSTOCK!$I$3:$I$6125))} -> 409 | I109: =ARRAY_CONSTRAIN(ARRAYFORMULA(SUM(IF([3]!Table13[ID]=B109,[3]!Table13[QTY]))), 1, 1) -> #ERROR! | J109: =TABLEITEM!$H$3:$H$2749-TABLEITEM!$I$3:$I$2749 -> #ERROR!
A110: 413 | B110: PL16-6 | D110: หางปลากลมเปลือยหนา 16-6 | E110: T.LUG | F110: EA | G110: {=MAX(IF(INSTOCK!$H$3:$H$6125=B110,INSTOCK!$K$3:$K$6125))} -> 7.5 | H110: {=SUM(IF(INSTOCK!$H$3:$H$6125=B110,INSTOCK!$I$3:$I$6125))} -> 500 | I110: =ARRAY_CONSTRAIN(ARRAYFORMULA(SUM(IF([3]!Table13[ID]=B110,[3]!Table13[QTY]))), 1, 1) -> #ERROR! | J110: =TABLEITEM!$H$3:$H$2749-TABLEITEM!$I$3:$I$2749 -> #ERROR!
A111: 404 | B111: R6-8 | D111: หางปลากลมเปลือย6-8 | E111: LIB | F111: EA | G111: {=MAX(IF(INSTOCK!$H$3:$H$6125=B111,INSTOCK!$K$3:$K$6125))} -> 2.19 | H111: {=SUM(IF(INSTOCK!$H$3:$H$6125=B111,INSTOCK!$I$3:$I$6125))} -> 1501 | I111: =ARRAY_CONSTRAIN(ARRAYFORMULA(SUM(IF([3]!Table13[ID]=B111,[3]!Table13[QTY]))), 1, 1) -> #ERROR! | J111: =TABLEITEM!$H$3:$H$2749-TABLEITEM!$I$3:$I$2749 -> #ERROR!
A112: 403 | B112: R6-6 | D112: หางปลากลมเปลือย6-6 | E112: T.LUG | F112: EA | G112: {=MAX(IF(INSTOCK!$H$3:$H$6125=B112,INSTOCK!$K$3:$K$6125))} -> 2.5 | H112: {=SUM(IF(INSTOCK!$H$3:$H$6125=B112,INSTOCK!$I$3:$I$6125))} -> 4610 | I112: =ARRAY_CONSTRAIN(ARRAYFORMULA(SUM(IF([3]!Table13[ID]=B112,[3]!Table13[QTY]))), 1, 1) -> #ERROR! | J112: =TABLEITEM!$H$3:$H$2749-TABLEITEM!$I$3:$I$2749 -> #ERROR!
... A171: 407 | B171: R8-10 | D171: หางปลากลมปลือย8-10 | E171: LIB | F171: EA | G171: {=MAX(IF(INSTOCK!$H$3:$H$6125=B171,INSTOCK!$K$3:$K$6125))} -> 5.5 | H171: {=SUM(IF(INSTOCK!$H$3:$H$6125=B171,INSTOCK!$I$3:$I$6125))} -> 1133 | I171: =ARRAY_CONSTRAIN(ARRAYFORMULA(SUM(IF([3]!Table13[ID]=B171,[3]!Table13[QTY]))), 1, 1) -> #ERROR! | J171: =TABLEITEM!$H$3:$H$2749-TABLEITEM!$I$3:$I$2749 -> #ERROR!
B172: HAKKO-130W | D172: หัวแร้งเชื่อมตะกั่ว 130W รุ่น NO.980F-V22 | E172: HAKKO | F172: EA | G172: {=MAX(IF(INSTOCK!$H$3:$H$6125=B172,INSTOCK!$K$3:$K$6125))} -> 650 | H172: {=SUM(IF(INSTOCK!$H$3:$H$6125=B172,INSTOCK!$I$3:$I$6125))} -> 2 | I172: =ARRAY_CONSTRAIN(ARRAYFORMULA(SUM(IF([3]!Table13[ID]=B172,[3]!Table13[QTY]))), 1, 1) -> #ERROR! | J172: =TABLEITEM!$H$3:$H$2749-TABLEITEM!$I$3:$I$2749 -> #ERROR!
B173: WNM8 | D173: หัวน้อตหางปลาเหล็กเหนียว M8 | E173: KM | F173: EA | G173: {=MAX(IF(INSTOCK!$H$3:$H$6125=B173,INSTOCK!$K$3:$K$6125))} -> 0 | H173: {=SUM(IF(INSTOCK!$H$3:$H$6125=B173,INSTOCK!$I$3:$I$6125))} -> 0 | I173: =ARRAY_CONSTRAIN(ARRAYFORMULA(SUM(IF([3]!Table13[ID]=B173,[3]!Table13[QTY]))), 1, 1) -> #ERROR! | J173: =TABLEITEM!$H$3:$H$2749-TABLEITEM!$I$3:$I$2749 -> #ERROR!
B174: WNM6 | D174: หัวน้อตหางปลาเหล็กเหนียว M6 | E174: TPC | F174: EA | G174: {=MAX(IF(INSTOCK!$H$3:$H$6125=B174,INSTOCK!$K$3:$K$6125))} -> 0 | H174: {=SUM(IF(INSTOCK!$H$3:$H$6125=B174,INSTOCK!$I$3:$I$6125))} -> 0 | I174: =ARRAY_CONSTRAIN(ARRAYFORMULA(SUM(IF([3]!Table13[ID]=B174,[3]!Table13[QTY]))), 1, 1) -> #ERROR! | J174: =TABLEITEM!$H$3:$H$2749-TABLEITEM!$I$3:$I$2749 -> #ERROR!
B175: WNM10 | D175: หัวน้อตหางปลาเหล็กเหนียว M10 | E175: TREETOOL | F175: EA | G175: {=MAX(IF(INSTOCK!$H$3:$H$6125=B175,INSTOCK!$K$3:$K$6125))} -> 4.8 | H175: {=SUM(IF(INSTOCK!$H$3:$H$6125=B175,INSTOCK!$I$3:$I$6125))} -> 100 | I175: =ARRAY_CONSTRAIN(ARRAYFORMULA(SUM(IF([3]!Table13[ID]=B175,[3]!Table13[QTY]))), 1, 1) -> #ERROR! | J175: =TABLEITEM!$H$3:$H$2749-TABLEITEM!$I$3:$I$2749 -> #ERROR!
B176: LN8 | D176: หัวน็อตล็อค M8 | E176: KM | F176: EA | G176: {=MAX(IF(INSTOCK!$H$3:$H$6125=B176,INSTOCK!$K$3:$K$6125))} -> 0.77 | H176: {=SUM(IF(INSTOCK!$H$3:$H$6125=B176,INSTOCK!$I$3:$I$6125))} -> 500 | I176: =ARRAY_CONSTRAIN(ARRAYFORMULA(SUM(IF([3]!Table13[ID]=B176,[3]!Table13[QTY]))), 1, 1) -> #ERROR! | J176: =TABLEITEM!$H$3:$H$2749-TABLEITEM!$I$3:$I$2749 -> #ERROR!
B177: LN6 | D177: หัวน็อตล็อค M6 | E177: TREETOOL | F177: EA | G177: {=MAX(IF(INSTOCK!$H$3:$H$6125=B177,INSTOCK!$K$3:$K$6125))} -> 0 | H177: {=SUM(IF(INSTOCK!$H$3:$H$6125=B177,INSTOCK!$I$3:$I$6125))} -> 0 | I177: =ARRAY_CONSTRAIN(ARRAYFORMULA(SUM(IF([3]!Table13[ID]=B177,[3]!Table13[QTY]))), 1, 1) -> #ERROR! | J177: =TABLEITEM!$H$3:$H$2749-TABLEITEM!$I$3:$I$2749 -> #ERROR!
B178: LN5 | D178: หัวน็อตล็อค M5 | E178: KM | F178: EA | G178: {=MAX(IF(INSTOCK!$H$3:$H$6125=B178,INSTOCK!$K$3:$K$6125))} -> 0.3 | H178: {=SUM(IF(INSTOCK!$H$3:$H$6125=B178,INSTOCK!$I$3:$I$6125))} -> 4000 | I178: =ARRAY_CONSTRAIN(ARRAYFORMULA(SUM(IF([3]!Table13[ID]=B178,[3]!Table13[QTY]))), 1, 1) -> #ERROR! | J178: =TABLEITEM!$H$3:$H$2749-TABLEITEM!$I$3:$I$2749 -> #ERROR!
B179: LN4 | D179: หัวน็อตล็อค M4 | E179: KM | F179: EA | G179: {=MAX(IF(INSTOCK!$H$3:$H$6125=B179,INSTOCK!$K$3:$K$6125))} -> 0.3 | H179: {=SUM(IF(INSTOCK!$H$3:$H$6125=B179,INSTOCK!$I$3:$I$6125))} -> 11000 | I179: =ARRAY_CONSTRAIN(ARRAYFORMULA(SUM(IF([3]!Table13[ID]=B179,[3]!Table13[QTY]))), 1, 1) -> #ERROR! | J179: =TABLEITEM!$H$3:$H$2749-TABLEITEM!$I$3:$I$2749 -> #ERROR!
B180: LN10 | D180: หัวน็อตล็อค M10 | E180: KM | F180: EA | G180: {=MAX(IF(INSTOCK!$H$3:$H$6125=B180,INSTOCK!$K$3:$K$6125))} -> 0.9 | H180: {=SUM(IF(INSTOCK!$H$3:$H$6125=B180,INSTOCK!$I$3:$I$6125))} -> 200 | I180: =ARRAY_CONSTRAIN(ARRAYFORMULA(SUM(IF([3]!Table13[ID]=B180,[3]!Table13[QTY]))), 1, 1) -> #ERROR! | J180: =TABLEITEM!$H$3:$H$2749-TABLEITEM!$I$3:$I$2749 -> #ERROR!
B181: SN10SUS | D181: หัวน๊อต SUS M10 | E181: AS | F181: EA | G181: {=MAX(IF(INSTOCK!$H$3:$H$6125=B181,INSTOCK!$K$3:$K$6125))} -> 10 | H181: {=SUM(IF(INSTOCK!$H$3:$H$6125=B181,INSTOCK!$I$3:$I$6125))} -> 4311 | I181: =ARRAY_CONSTRAIN(ARRAYFORMULA(SUM(IF([3]!Table13[ID]=B181,[3]!Table13[QTY]))), 1, 1) -> #ERROR! | J181: =TABLEITEM!$H$3:$H$2749-TABLEITEM!$I$3:$I$2749 -> #ERROR!
B182: SN-5/8" | D182: หัวน๊อต SUS 5/8" 11x26x13 BSW | F182: EA | G182: {=MAX(IF(INSTOCK!$H$3:$H$6125=B182,INSTOCK!$K$3:$K$6125))} -> 11 | H182: {=SUM(IF(INSTOCK!$H$3:$H$6125=B182,INSTOCK!$I$3:$I$6125))} -> 24 | I182: =ARRAY_CONSTRAIN(ARRAYFORMULA(SUM(IF([3]!Table13[ID]=B182,[3]!Table13[QTY]))), 1, 1) -> #ERROR! | J182: =TABLEITEM!$H$3:$H$2749-TABLEITEM!$I$3:$I$2749 -> #ERROR!
B183: SN8HDG | D183: หัวน้อต M8 HDG | E183: KM | F183: EA | G183: {=MAX(IF(INSTOCK!$H$3:$H$6125=B183,INSTOCK!$K$3:$K$6125))} -> 1.3 | H183: {=SUM(IF(INSTOCK!$H$3:$H$6125=B183,INSTOCK!$I$3:$I$6125))} -> 7000 | I183: =ARRAY_CONSTRAIN(ARRAYFORMULA(SUM(IF([3]!Table13[ID]=B183,[3]!Table13[QTY]))), 1, 1) -> #ERROR! | J183: =TABLEITEM!$H$3:$H$2749-TABLEITEM!$I$3:$I$2749 -> #ERROR!
B184: SN3Z | D184: หัวน้อต M3 ชุบขาว | E184: KM | F184: EA | G184: {=MAX(IF(INSTOCK!$H$3:$H$6125=B184,INSTOCK!$K$3:$K$6125))} -> 0.18 | H184: {=SUM(IF(INSTOCK!$H$3:$H$6125=B184,INSTOCK!$I$3:$I$6125))} -> 3000 | I184: =ARRAY_CONSTRAIN(ARRAYFORMULA(SUM(IF([3]!Table13[ID]=B184,[3]!Table13[QTY]))), 1, 1) -> #ERROR! | J184: =TABLEITEM!$H$3:$H$2749-TABLEITEM!$I$3:$I$2749 -> #ERROR!
B185: SN10HDG | D185: หัวน้อต M10 HDG | E185: KM | F185: EA | G185: {=MAX(IF(INSTOCK!$H$3:$H$6125=B185,INSTOCK!$K$3:$K$6125))} -> 1.495 | H185: {=SUM(IF(INSTOCK!$H$3:$H$6125=B185,INSTOCK!$I$3:$I$6125))} -> 24970 | I185: =ARRAY_CONSTRAIN(ARRAYFORMULA(SUM(IF([3]!Table13[ID]=B185,[3]!Table13[QTY]))), 1, 1) -> #ERROR! | J185: =TABLEITEM!$H$3:$H$2749-TABLEITEM!$I$3:$I$2749 -> #ERROR!
B186: SN8 | D186: หัวน็อต M 8 ชุบขาว | E186: KM | F186: EA | G186: {=MAX(IF(INSTOCK!$H$3:$H$6125=B186,INSTOCK!$K$3:$K$6125))} -> 0.468 | H186: {=SUM(IF(INSTOCK!$H$3:$H$6125=B186,INSTOCK!$I$3:$I$6125))} -> 215000 | I186: =ARRAY_CONSTRAIN(ARRAYFORMULA(SUM(IF([3]!Table13[ID]=B186,[3]!Table13[QTY]))), 1, 1) -> #ERROR! | J186: =TABLEITEM!$H$3:$H$2749-TABLEITEM!$I$3:$I$2749 -> #ERROR!
B187: SN8SUS | D187: หัวน็อต สแตนเลส M8 | E187: KM | F187: EA | G187: {=MAX(IF(INSTOCK!$H$3:$H$6125=B187,INSTOCK!$K$3:$K$6125))} -> 1.4 | H187: {=SUM(IF(INSTOCK!$H$3:$H$6125=B187,INSTOCK!$I$3:$I$6125))} -> 2500 | I187: =ARRAY_CONSTRAIN(ARRAYFORMULA(SUM(IF([3]!Table13[ID]=B187,[3]!Table13[QTY]))), 1, 1) -> #ERROR! | J187: =TABLEITEM!$H$3:$H$2749-TABLEITEM!$I$3:$I$2749 -> #ERROR!
B188: SN6SUS | D188: หัวน็อต สแตนเลส M6 | E188: KM | F188: EA | G188: {=MAX(IF(INSTOCK!$H$3:$H$6125=B188,INSTOCK!$K$3:$K$6125))} -> 0.45 | H188: {=SUM(IF(INSTOCK!$H$3:$H$6125=B188,INSTOCK!$I$3:$I$6125))} -> 25500 | I188: =ARRAY_CONSTRAIN(ARRAYFORMULA(SUM(IF([3]!Table13[ID]=B188,[3]!Table13[QTY]))), 1, 1) -> #ERROR! | J188: =TABLEITEM!$H$3:$H$2749-TABLEITEM!$I$3:$I$2749 -> #ERROR!
B189: SN5SUS | D189: หัวน็อต สแตนเลส M5 | E189: KM | F189: EA | G189: {=MAX(IF(INSTOCK!$H$3:$H$6125=B189,INSTOCK!$K$3:$K$6125))} -> 0.4275 | H189: {=SUM(IF(INSTOCK!$H$3:$H$6125=B189,INSTOCK!$I$3:$I$6125))} -> 2000 | I189: =ARRAY_CONSTRAIN(ARRAYFORMULA(SUM(IF([3]!Table13[ID]=B189,[3]!Table13[QTY]))), 1, 1) -> #ERROR! | J189: =TABLEITEM!$H$3:$H$2749-TABLEITEM!$I$3:$I$2749 -> #ERROR!
B190: SN4SUS | D190: หัวน็อต สแตนเลส M4 | E190: KM | F190: EA | G190: {=MAX(IF(INSTOCK!$H$3:$H$6125=B190,INSTOCK!$K$3:$K$6125))} -> 0 | H190: {=SUM(IF(INSTOCK!$H$3:$H$6125=B190,INSTOCK!$I$3:$I$6125))} -> 0 | I190: =ARRAY_CONSTRAIN(ARRAYFORMULA(SUM(IF([3]!Table13[ID]=B190,[3]!Table13[QTY]))), 1, 1) -> #ERROR! | J190: =TABLEITEM!$H$3:$H$2749-TABLEITEM!$I$3:$I$2749 -> #ERROR!
B191: SN6 | D191: หัวน็อต M 6 ชุบขาว | E191: KM | F191: EA | G191: {=MAX(IF(INSTOCK!$H$3:$H$6125=B191,INSTOCK!$K$3:$K$6125))} -> 0.16 | H191: {=SUM(IF(INSTOCK!$H$3:$H$6125=B191,INSTOCK!$I$3:$I$6125))} -> 51000 | I191: =ARRAY_CONSTRAIN(ARRAYFORMULA(SUM(IF([3]!Table13[ID]=B191,[3]!Table13[QTY]))), 1, 1) -> #ERROR! | J191: =TABLEITEM!$H$3:$H$2749-TABLEITEM!$I$3:$I$2749 -> #ERROR!
B192: SN5Z | D192: หัวน้อต M5 ชุบขาว | E192: KM | F192: EA | G192: {=MAX(IF(INSTOCK!$H$3:$H$6125=B192,INSTOCK!$K$3:$K$6125))} -> 0.3 | H192: {=SUM(IF(INSTOCK!$H$3:$H$6125=B192,INSTOCK!$I$3:$I$6125))} -> 5000 | I192: =ARRAY_CONSTRAIN(ARRAYFORMULA(SUM(IF([3]!Table13[ID]=B192,[3]!Table13[QTY]))), 1, 1) -> #ERROR! | J192: =TABLEITEM!$H$3:$H$2749-TABLEITEM!$I$3:$I$2749 -> #ERROR!
B193: SN4Z | D193: หัวน้อต M4 ชุบขาว | E193: KM | F193: EA | G193: {=MAX(IF(INSTOCK!$H$3:$H$6125=B193,INSTOCK!$K$3:$K$6125))} -> 0.3 | H193: {=SUM(IF(INSTOCK!$H$3:$H$6125=B193,INSTOCK!$I$3:$I$6125))} -> 52000 | I193: =ARRAY_CONSTRAIN(ARRAYFORMULA(SUM(IF([3]!Table13[ID]=B193,[3]!Table13[QTY]))), 1, 1) -> #ERROR! | J193: =TABLEITEM!$H$3:$H$2749-TABLEITEM!$I$3:$I$2749 -> #ERROR!
B194: SN16 | D194: หัวน้อต M16 ชุบขาว | E194: KM | F194: EA | G194: {=MAX(IF(INSTOCK!$H$3:$H$6125=B194,INSTOCK!$K$3:$K$6125))} -> 3.2 | H194: {=SUM(IF(INSTOCK!$H$3:$H$6125=B194,INSTOCK!$I$3:$I$6125))} -> 200 | I194: =ARRAY_CONSTRAIN(ARRAYFORMULA(SUM(IF([3]!Table13[ID]=B194,[3]!Table13[QTY]))), 1, 1) -> #ERROR! | J194: =TABLEITEM!$H$3:$H$2749-TABLEITEM!$I$3:$I$2749 -> #ERROR!
... B197: LSSL-003 | D197: ห่วงล็อคสเตนเลสเล็ก มีสปริง 18x45 | E197: แพนสยาม | F197: EA | G197: {=MAX(IF(INSTOCK!$H$3:$H$6125=B197,INSTOCK!$K$3:$K$6125))} -> 21 | H197: {=SUM(IF(INSTOCK!$H$3:$H$6125=B197,INSTOCK!$I$3:$I$6125))} -> 2000 | I197: =ARRAY_CONSTRAIN(ARRAYFORMULA(SUM(IF([3]!Table13[ID]=B197,[3]!Table13[QTY]))), 1, 1) -> #ERROR! | J197: =TABLEITEM!$H$3:$H$2749-TABLEITEM!$I$3:$I$2749 -> #ERROR!
B198: EBM16 | D198: ห่วงตู้ M16 | F198: EA | G198: {=MAX(IF(INSTOCK!$H$3:$H$6125=B198,INSTOCK!$K$3:$K$6125))} -> 0 | H198: {=SUM(IF(INSTOCK!$H$3:$H$6125=B198,INSTOCK!$I$3:$I$6125))} -> 0 | I198: =ARRAY_CONSTRAIN(ARRAYFORMULA(SUM(IF([3]!Table13[ID]=B198,[3]!Table13[QTY]))), 1, 1) -> #ERROR! | J198: =TABLEITEM!$H$3:$H$2749-TABLEITEM!$I$3:$I$2749 -> #ERROR!
B199: EBM12 | D199: ห่วงตู้ M12 ชุบขาว | F199: EA | G199: {=MAX(IF(INSTOCK!$H$3:$H$6125=B199,INSTOCK!$K$3:$K$6125))} -> 30 | H199: {=SUM(IF(INSTOCK!$H$3:$H$6125=B199,INSTOCK!$I$3:$I$6125))} -> 2200 | I199: =ARRAY_CONSTRAIN(ARRAYFORMULA(SUM(IF([3]!Table13[ID]=B199,[3]!Table13[QTY]))), 1, 1) -> #ERROR! | J199: =TABLEITEM!$H$3:$H$2749-TABLEITEM!$I$3:$I$2749 -> #ERROR!
B200: EBM10 | D200: ห่วงตู้ M10 | F200: EA | G200: {=MAX(IF(INSTOCK!$H$3:$H$6125=B200,INSTOCK!$K$3:$K$6125))} -> 30 | H200: {=SUM(IF(INSTOCK!$H$3:$H$6125=B200,INSTOCK!$I$3:$I$6125))} -> 300 | I200: =ARRAY_CONSTRAIN(ARRAYFORMULA(SUM(IF([3]!Table13[ID]=B200,[3]!Table13[QTY]))), 1, 1) -> #ERROR! | J200: =TABLEITEM!$H$3:$H$2749-TABLEITEM!$I$3:$I$2749 -> #ERROR!
B201: HPL-N400 | D201: หลอดแสงจันทร์ HPL-N400W | E201: PL | F201: EA | G201: {=MAX(IF(INSTOCK!$H$3:$H$6125=B201,INSTOCK!$K$3:$K$6125))} -> 235 | H201: {=SUM(IF(INSTOCK!$H$3:$H$6125=B201,INSTOCK!$I$3:$I$6125))} -> 31 | I201: =ARRAY_CONSTRAIN(ARRAYFORMULA(SUM(IF([3]!Table13[ID]=B201,[3]!Table13[QTY]))), 1, 1) -> #ERROR! | J201: =TABLEITEM!$H$3:$H$2749-TABLEITEM!$I$3:$I$2749 -> #ERROR!
B202: PL-ESS-3W | D202: หลอดปิงปองESS/บับ 3W/WW-PL/E | E202: PL | F202: EA | G202: {=MAX(IF(INSTOCK!$H$3:$H$6125=B202,INSTOCK!$K$3:$K$6125))} -> 60 | H202: {=SUM(IF(INSTOCK!$H$3:$H$6125=B202,INSTOCK!$I$3:$I$6125))} -> 62 | I202: =ARRAY_CONSTRAIN(ARRAYFORMULA(SUM(IF([3]!Table13[ID]=B202,[3]!Table13[QTY]))), 1, 1) -> #ERROR! | J202: =TABLEITEM!$H$3:$H$2749-TABLEITEM!$I$3:$I$2749 -> #ERROR!
B203: TLD-36W | D203: หลอดนีออน 36W | E203: PL | F203: EA | G203: {=MAX(IF(INSTOCK!$H$3:$H$6125=B203,INSTOCK!$K$3:$K$6125))} -> 38 | H203: {=SUM(IF(INSTOCK!$H$3:$H$6125=B203,INSTOCK!$I$3:$I$6125))} -> 74 | I203: =ARRAY_CONSTRAIN(ARRAYFORMULA(SUM(IF([3]!Table13[ID]=B203,[3]!Table13[QTY]))), 1, 1) -> #ERROR! | J203: =TABLEITEM!$H$3:$H$2749-TABLEITEM!$I$3:$I$2749 -> #ERROR!
B204: LED-9W | D204: หลอด LED/บับ 9W/PL WARMWHITE | E204: PL | F204: EA | G204: {=MAX(IF(INSTOCK!$H$3:$H$6125=B204,INSTOCK!$K$3:$K$6125))} -> 95 | H204: {=SUM(IF(INSTOCK!$H$3:$H$6125=B204,INSTOCK!$I$3:$I$6125))} -> 12 | I204: =ARRAY_CONSTRAIN(ARRAYFORMULA(SUM(IF([3]!Table13[ID]=B204,[3]!Table13[QTY]))), 1, 1) -> #ERROR! | J204: =TABLEITEM!$H$3:$H$2749-TABLEITEM!$I$3:$I$2749 -> #ERROR!
B205: LED-10.5W | D205: หลอด LED/บับ 10.5-85W/65K-PL | E205: PL | F205: EA | G205: {=MAX(IF(INSTOCK!$H$3:$H$6125=B205,INSTOCK!$K$3:$K$6125))} -> 146 | H205: {=SUM(IF(INSTOCK!$H$3:$H$6125=B205,INSTOCK!$I$3:$I$6125))} -> 46 | I205: =ARRAY_CONSTRAIN(ARRAYFORMULA(SUM(IF([3]!Table13[ID]=B205,[3]!Table13[QTY]))), 1, 1) -> #ERROR! | J205: =TABLEITEM!$H$3:$H$2749-TABLEITEM!$I$3:$I$2749 -> #ERROR!
A206: 306 | B206: PP | D206: หมุดเนมเพลท | E206: CPT | F206: EA | G206: {=MAX(IF(INSTOCK!$H$3:$H$6125=B206,INSTOCK!$K$3:$K$6125))} -> 1.5 | H206: {=SUM(IF(INSTOCK!$H$3:$H$6125=B206,INSTOCK!$I$3:$I$6125))} -> 7087 | I206: =ARRAY_CONSTRAIN(ARRAYFORMULA(SUM(IF([3]!Table13[ID]=B206,[3]!Table13[QTY]))), 1, 1) -> #ERROR! | J206: =TABLEITEM!$H$3:$H$2749-TABLEITEM!$I$3:$I$2749 -> #ERROR!
B207: PIN | D207: หมุด | E207: SPECIAL DIE | F207: EA | G207: {=MAX(IF(INSTOCK!$H$3:$H$6125=B207,INSTOCK!$K$3:$K$6125))} -> 0 | H207: {=SUM(IF(INSTOCK!$H$3:$H$6125=B207,INSTOCK!$I$3:$I$6125))} -> 0 | I207: =ARRAY_CONSTRAIN(ARRAYFORMULA(SUM(IF([3]!Table13[ID]=B207,[3]!Table13[QTY]))), 1, 1) -> #ERROR! | J207: =TABLEITEM!$H$3:$H$2749-TABLEITEM!$I$3:$I$2749 -> #ERROR!
B208: TR-2822 | D208: หม้อแปลง Tranformer TR-2822 1ph SW 220V 50-60Hz/24V 50VA | E208: TESLA | F208: EA | G208: {=MAX(IF(INSTOCK!$H$3:$H$6125=B208,INSTOCK!$K$3:$K$6125))} -> 278.3 | H208: {=SUM(IF(INSTOCK!$H$3:$H$6125=B208,INSTOCK!$I$3:$I$6125))} -> 23 | I208: =ARRAY_CONSTRAIN(ARRAYFORMULA(SUM(IF([3]!Table13[ID]=B208,[3]!Table13[QTY]))), 1, 1) -> #ERROR! | J208: =TABLEITEM!$H$3:$H$2749-TABLEITEM!$I$3:$I$2749 -> #ERROR!
...

Sheet REPORTIN
I1: ID | J1: BS
A2: SUPPLIER | B2: (All) | I2: LIST | J2: (All)
A3: IV No. | B3: IV6103151
A4: PO No. | B4: (All) | M4: Values
A5: PC Job | B5: (Multiple Items) | I5: SUPPLIER | J5: DATE | K5: IV No. | L5: UNIT/Price | M5: Sum of QTY | N5: Sum of Total
I6: (blank) | J6: 43199 | K6: ยอดยกมา17 | L6: 40 | M6: 360 | N6: 14400
C7: Values | I7: บอร์เนียว | J7: 43132 | K7: 0418G00694 | L7: 45 | M7: 400 | N7: 18000
A8: ID | B8: LIST | C8: Average of UNIT/Price | D8: Sum of QTY | E8: Sum of Total | J8: 43161 | K8: 0418G01413 | L8: 45 | M8: 300 | N8: 13500
A9: BAR 100x10 | B9: บัสบาร์ทองแดง 100x10 | C9: 2145.6 | D9: 25 | E9: 53640 | J9: 43164 | K9: 0418G01472 | L9: 45 | M9: 100 | N9: 4500
A10: BAR 15X3 | B10: บัสบาร์ทองแดง 15x3 | C10: 100.8 | D10: 100 | E10: 10080 | J10: 43207 | K10: 418030840 | L10: 45 | M10: 400 | N10: 18000
A11: Grand Total | C11: 1123.2 | D11: 125 | E11: 63720 | J11: 43237 | K11: 418040607 | L11: 45 | M11: 400 | N11: 18000
J12: 43262 | K12: 418047550 | L12: 45 | M12: 400 | N12: 18000
J13: 43304 | K13: 418064683 | L13: 45 | M13: 400 | N13: 18000
J14: 43348 | K14: 418074872 | L14: 45 | M14: 400 | N14: 18000
J15: 43405 | K15: 0418G07328 | L15: 45 | M15: 400 | N15: 18000
J16: 43543 | K16: 419026590 | L16: 45 | M16: 400 | N16: 18000
J17: 43600 | K17: 419042156 | L17: 45 | M17: 400 | N17: 18000
J18: 43654 | K18: 419058888 | L18: 45 | M18: 400 | N18: 18000
J19: 43719 | K19: 419079291 | L19: 45 | M19: 400 | N19: 18000
J20: 43770 | K20: 0419G07266 | L20: 45 | M20: 400 | N20: 18000
I21: Grand Total | M21: 5560 | N21: 248400
